Workbook

Sheet Executive Summary
B1: ="Financial Model:" & 'Data Sheet'!B1 -> Financial Model:TITAN COMPANY LTD
B3: Company Snapshot
B5: Parameter | C5: Details
B7: Company Name | C7: Titan Company Limited
B8: Ticker Symbol | C8: TITAN
B9: Sector / Industry | C9: Consumer Durables / Retail & Lifestyle
B10: Headquarters | C10: Bengaluru, Karnataka, India
B11: Founded Year | C11: 1984
B12: Managing Director & CEO | C12: Ajoy Chawla
B13: Listed Exchanges | C13: NSE & BSE
B14: Index Membership | C14: NIFTY 50, SENSEX, NIFTY Consumer Durables
B16: CORE PRODUCTS & KEY BRANDS
B18: Category | C18: Key Brands
B19: Jewelry | C19: Tanishq, CaratLane, Mia, Zoya
B20: Watches & Wearables | C20: Titan, Fastrack, Sonata, Helios, Xylys
B21: Eyewear | C21: Titan Eye+, Fastrack Eyewear
B22: Emerging Categories | C22: Skinn (Fragrances), Taneira (Sarees)
B23: Export / International Markets | C23: Middle East (UAE, Qatar), USA, Canada, Singapore
B25: VALUATION & MARKET DATA
B27: Current Market Price (CMP) | C27: 4516
B28: Market Capitalization (Cr) | C28: 400900
B29: Current Shares Outstanding (Cr) | C29: 88.77
B30: Base Historical Year | C30: FY26
B31: Projection Period | C31: FY27 - FY31

Sheet Assumptions and Drivers

Sheet Assumptions
B2: Assumption | C2: Value | D2: Source or reason
B3: Valuation date | C3: 46112 | D3: Date of the latest balance sheet
B4: Tax rate | C4: =WACC!G10 -> 0.2517 | D4: 22% base, 10% surcharge and 4% cess
B5: Risk-free rate | C5: =WACC!K23 -> 0.072 | D5: India 10-year government bond yield
B6: Market return | C6: =Rm!F7 -> 0.16449231 | D6: Average Nifty annual return 2000-2025 plus dividend yield (Rm sheet)
B7: Equity risk premium | C7: =WACC!K24 -> 0.092492308 | D7: Market return minus risk-free rate
B8: Beta | C8: =WACC!K25 -> 1.2 | D8: Median unlevered beta of peers, relevered at target debt/equity
B9: Cost of equity | C9: =WACC!K38 -> 0.18299077 | D9: Risk-free rate + beta x equity risk premium
B10: Pre-tax cost of debt | C10: =WACC!E23 -> 0.038535645 | D10: Interest expense divided by total debt
B11: Post-tax cost of debt | C11: =WACC!E25 -> 0.028836224 | D11: Pre-tax cost of debt x (1 - tax rate)
B12: Weight of equity | C12: =WACC!E33 -> 0.91509814 | D12: Target capital structure based on peer median
B13: Weight of debt | C13: =WACC!E32 -> 0.084901857 | D13: Target capital structure based on peer median
B14: WACC | C14: =WACC!K43 -> 0.16990276 | D14: Weighted average of cost of equity and post-tax cost of debt
B15: Expected growth, Mar-27 to Mar-31 | C15: =DCF!F18 -> 0.21061257 | D15: Median intrinsic growth rate over 4 years (reinvestment rate x ROIC)
B16: Reinvestment rate, forecast years | C16: 0.75 | D16: Share of NOPAT reinvested each year; expected growth divided by ROIC
B17: Terminal growth | C17: =DCF!D26 -> 0.0575 | D17: Long-run nominal growth of the Indian economy
B18: Terminal ROIC | C18: =DCF!D25 -> 0.16990276 | D18: Set equal to WACC
B19: Terminal reinvestment rate | C19: =C17/C18 -> 0.33842887 | D19: Terminal growth divided by terminal ROIC
B20: Discounting | C20: Mid-year convention | D20: Cash flows assumed to arrive evenly through each year
B21: Current market price (Rs) | C21: ='Data Sheet'!B8 -> 4515.7 | D21: Screener; 4/10/2026
B22: Shares outstanding (crore) | C22: ='Data Sheet'!B6 -> 88.778617 | D22: Screener
B23: Cash (Rs crore) | C23: =DCF!E35 -> 1917 | D23: Balance sheet, Mar-26
B24: Debt (Rs crore) | C24: =DCF!E36 -> 27448 | D24: Long-term and short-term borrowings, Mar-26
B25: Equity value per share (Rs) | C25: =DCF!E40 -> 350.66693 | D25: Model output

Sheet Historical_FS
B1: ="Financial Model:" & 'Data Sheet'!B1 -> Financial Model:TITAN COMPANY LTD
B2: Historical Financial Statements
B3: Year | C3: 42825 | D3: 43190 | E3: 43555 | F3: 43921 | G3: 44286 | H3: 44651 | I3: 45016 | J3: 45382 | K3: 45747 | L3: 46112
B5: #Income Statement
B7: Sales | C7: =IFERROR('Data Sheet'!B17,0) -> 13260.83 | D7: =IFERROR('Data Sheet'!C17,0) -> 16119.77 | E7: =IFERROR('Data Sheet'!D17,0) -> 19778.52 | F7: =IFERROR('Data Sheet'!E17,0) -> 21052 | G7: =IFERROR('Data Sheet'!F17,0) -> 21644 | H7: =IFERROR('Data Sheet'!G17,0) -> 28799 | I7: =IFERROR('Data Sheet'!H17,0) -> 40575 | J7: =IFERROR('Data Sheet'!I17,0) -> 51084 | ... L7: =IFERROR('Data Sheet'!K17,0) -> 87584
B8: Sales Growth % | C8: - | D8: =(D7/C7)-1 -> 0.21559284 | E8: =(E7/D7)-1 -> 0.22697284 | F8: =(F7/E7)-1 -> 0.064387022 | G8: =(G7/F7)-1 -> 0.028120844 | H8: =(H7/G7)-1 -> 0.3305766 | I8: =(I7/H7)-1 -> 0.40890309 | J8: =(J7/I7)-1 -> 0.25900185 | K8: =(K7/J7)-1 -> 0.18346253 | L8: =(L7/K7)-1 -> 0.44872304
B10: COGS | C10: =IFERROR(SUM('Data Sheet'!B18,'Data Sheet'!B20:B21)-'Data Sheet'!B19,0) -> 9711.69 | D10: =IFERROR(SUM('Data Sheet'!C18,'Data Sheet'!C20:C21)-'Data Sheet'!C19,0) -> 11856.37 | E10: =IFERROR(SUM('Data Sheet'!D18,'Data Sheet'!D20:D21)-'Data Sheet'!D19,0) -> 14636.04 | F10: =IFERROR(SUM('Data Sheet'!E18,'Data Sheet'!E20:E21)-'Data Sheet'!E19,0) -> 15422 | G10: =IFERROR(SUM('Data Sheet'!F18,'Data Sheet'!F20:F21)-'Data Sheet'!F19,0) -> 16592 | H10: =IFERROR(SUM('Data Sheet'!G18,'Data Sheet'!G20:G21)-'Data Sheet'!G19,0) -> 21869 | I10: =IFERROR(SUM('Data Sheet'!H18,'Data Sheet'!H20:H21)-'Data Sheet'!H19,0) -> 30639 | J10: =IFERROR(SUM('Data Sheet'!I18,'Data Sheet'!I20:I21)-'Data Sheet'!I19,0) -> 39789 | ... L10: =IFERROR(SUM('Data Sheet'!K18,'Data Sheet'!K20:K21)-'Data Sheet'!K19,0) -> 70769
B11: COGS % Sales | C11: =C10/C7 -> 0.73235914 | D11: =D10/D7 -> 0.73551732 | E11: =E10/E7 -> 0.73999672 | F11: =F10/F7 -> 0.73256698 | G11: =G10/G7 -> 0.76658658 | H11: =H10/H7 -> 0.75936664 | I11: =I10/I7 -> 0.75512015 | J11: =J10/J7 -> 0.77889359 | ... L11: =L10/L7 -> 0.80801288
B13: Gross Profit | C13: =C7-C10 -> 3549.14 | D13: =D7-D10 -> 4263.4 | E13: =E7-E10 -> 5142.48 | F13: =F7-F10 -> 5630 | G13: =G7-G10 -> 5052 | H13: =H7-H10 -> 6930 | I13: =I7-I10 -> 9936 | J13: =J7-J10 -> 11295 | ... L13: =L7-L10 -> 16815
B14: Gross Profit Margin | C14: =C13/C7 -> 0.26764086 | D14: =D13/D7 -> 0.26448268 | E14: =E13/E7 -> 0.26000328 | F14: =F13/F7 -> 0.26743302 | G14: =G13/G7 -> 0.23341342 | H14: =H13/H7 -> 0.24063336 | I14: =I13/I7 -> 0.24487985 | J14: =J13/J7 -> 0.22110641 | ... L14: =L13/L7 -> 0.19198712
B16: Selling & General Expenses | C16: =IFERROR(SUM('Data Sheet'!B22:B24),0) -> 2385.24 | D16: =IFERROR(SUM('Data Sheet'!C22:C24),0) -> 2619.2 | E16: =IFERROR(SUM('Data Sheet'!D22:D24),0) -> 3148.69 | F16: =IFERROR(SUM('Data Sheet'!E22:E24),0) -> 3167 | G16: =IFERROR(SUM('Data Sheet'!F22:F24),0) -> 3327 | H16: =IFERROR(SUM('Data Sheet'!G22:G24),0) -> 3586 | I16: =IFERROR(SUM('Data Sheet'!H22:H24),0) -> 5054 | J16: =IFERROR(SUM('Data Sheet'!I22:I24),0) -> 6003 | ... L16: =IFERROR(SUM('Data Sheet'!K22:K24),0) -> 8458
B17: S&G Exp % Sales | C17: =C16/C7 -> 0.17987109 | D17: =D16/D7 -> 0.16248371 | E17: =E16/E7 -> 0.15919745 | F17: =F16/F7 -> 0.15043701 | G17: =G16/G7 -> 0.15371466 | H17: =H16/H7 -> 0.12451821 | I17: =I16/I7 -> 0.12455946 | J17: =J16/J7 -> 0.11751233 | ... L17: =L16/L7 -> 0.09657015
B19: EBITDA | C19: =C13-C16 -> 1163.9 | D19: =D13-D16 -> 1644.2 | E19: =E13-E16 -> 1993.79 | F19: =F13-F16 -> 2463 | G19: =G13-G16 -> 1725 | H19: =H13-H16 -> 3344 | I19: =I13-I16 -> 4882 | J19: =J13-J16 -> 5292 | ... L19: =L13-L16 -> 8357
B20: EBITDA Margin | C20: =C19/C7 -> 0.08776977 | D20: =D19/D7 -> 0.10199897 | E20: =E19/E7 -> 0.10080582 | F20: =F19/F7 -> 0.11699601 | G20: =G19/G7 -> 0.079698762 | H20: =H19/H7 -> 0.11611514 | I20: =I19/I7 -> 0.12032039 | J20: =J19/J7 -> 0.10359408 | ... L20: =L19/L7 -> 0.095416971
B22: Interest | C22: =IFERROR('Data Sheet'!B27,0) -> 37.74 | D22: =IFERROR('Data Sheet'!C27,0) -> 52.92 | E22: =IFERROR('Data Sheet'!D27,0) -> 52.54 | F22: =IFERROR('Data Sheet'!E27,0) -> 166 | G22: =IFERROR('Data Sheet'!F27,0) -> 203 | H22: =IFERROR('Data Sheet'!G27,0) -> 218 | I22: =IFERROR('Data Sheet'!H27,0) -> 300 | J22: =IFERROR('Data Sheet'!I27,0) -> 619 | ... L22: =IFERROR('Data Sheet'!K27,0) -> 1180
B23: Interest % of Sales | C23: =C22/C7 -> 0.0028459757 | D23: =D22/D7 -> 0.0032829253 | E23: =E22/E7 -> 0.0026564172 | F23: =F22/F7 -> 0.0078852366 | G23: =G22/G7 -> 0.0093790427 | H23: =H22/H7 -> 0.0075697073 | I23: =I22/I7 -> 0.0073937153 | J23: =J22/J7 -> 0.012117297 | ... L23: =L22/L7 -> 0.01347278
B25: Depreciation | C25: =IFERROR('Data Sheet'!B26,0) -> 110.53 | D25: =IFERROR('Data Sheet'!C26,0) -> 131.43 | E25: =IFERROR('Data Sheet'!D26,0) -> 162.84 | F25: =IFERROR('Data Sheet'!E26,0) -> 348 | G25: =IFERROR('Data Sheet'!F26,0) -> 375 | H25: =IFERROR('Data Sheet'!G26,0) -> 399 | I25: =IFERROR('Data Sheet'!H26,0) -> 441 | J25: =IFERROR('Data Sheet'!I26,0) -> 584 | ... L25: =IFERROR('Data Sheet'!K26,0) -> 826
B26: Depreciation % of Sales | C26: =C25/C7 -> 0.008335074 | D26: =D25/D7 -> 0.0081533421 | E26: =E25/E7 -> 0.0082331742 | F26: =F25/F7 -> 0.016530496 | G26: =G25/G7 -> 0.017325818 | H26: =H25/H7 -> 0.013854648 | I26: =I25/I7 -> 0.010868762 | J26: =J25/J7 -> 0.011432151 | ... L26: =L25/L7 -> 0.0094309463
B28: Earnings Before Tax | C28: =C19+'Data Sheet'!B25-SUM(C22,C25) -> 973.25 | D28: =D19+'Data Sheet'!C25-SUM(D22,D25) -> 1529.78 | E28: =E19+'Data Sheet'!D25-SUM(E22,E25) -> 1956.89 | F28: =F19+'Data Sheet'!E25-SUM(F22,F25) -> 2102 | G28: =G19+'Data Sheet'!F25-SUM(G22,G25) -> 1327 | H28: =H19+'Data Sheet'!G25-SUM(H22,H25) -> 2904 | I28: =I19+'Data Sheet'!H25-SUM(I22,I25) -> 4447 | J28: =J19+'Data Sheet'!I25-SUM(J22,J25) -> 4623 | ... L28: =L19+'Data Sheet'!K25-SUM(L22,L25) -> 6801
B29: EBT % Sales | C29: =C28/C7 -> 0.073392842 | D29: =D28/D7 -> 0.094900858 | E29: =E28/E7 -> 0.098940163 | F29: =F28/F7 -> 0.099847995 | G29: =G28/G7 -> 0.061310294 | H29: =H28/H7 -> 0.10083683 | I29: =I28/I7 -> 0.10959951 | J29: =J28/J7 -> 0.090498003 | ... L29: =L28/L7 -> 0.077651169
B31: Tax | C31: =IFERROR('Data Sheet'!B29,0) -> 275.97 | D31: =IFERROR('Data Sheet'!C29,0) -> 427.87 | E31: =IFERROR('Data Sheet'!D29,0) -> 568.24 | F31: =IFERROR('Data Sheet'!E29,0) -> 609 | G31: =IFERROR('Data Sheet'!F29,0) -> 353 | H31: =IFERROR('Data Sheet'!G29,0) -> 706 | I31: =IFERROR('Data Sheet'!H29,0) -> 1173 | J31: =IFERROR('Data Sheet'!I29,0) -> 1127 | ... L31: =IFERROR('Data Sheet'!K29,0) -> 1728
B32: Effective Tax Rate | C32: =C31/C28 -> 0.2835551 | D32: =D31/D28 -> 0.27969381 | E32: =E31/E28 -> 0.29037912 | F32: =F31/F28 -> 0.28972407 | G32: =G31/G28 -> 0.26601356 | H32: =H31/H28 -> 0.24311295 | I32: =I31/I28 -> 0.26377333 | J32: =J31/J28 -> 0.24378109 | ... L32: =L31/L28 -> 0.25408028
B34: Net Profit | C34: =C28-C31 -> 697.28 | D34: =D28-D31 -> 1101.91 | E34: =E28-E31 -> 1388.65 | F34: =F28-F31 -> 1493 | G34: =G28-G31 -> 974 | H34: =H28-H31 -> 2198 | I34: =I28-I31 -> 3274 | J34: =J28-J31 -> 3496 | ... L34: =L28-L31 -> 5073
B35: Net Profit Margin | C35: =C34/C7 -> 0.052581927 | D35: =D34/D7 -> 0.068357675 | E35: =E34/E7 -> 0.070210006 | F35: =F34/F7 -> 0.070919628 | G35: =G34/G7 -> 0.045000924 | H35: =H34/H7 -> 0.076322095 | I35: =I34/I7 -> 0.08069008 | J35: =J34/J7 -> 0.068436301 | ... L35: =L34/L7 -> 0.057921538
B37: No of Equity Shares | C37: =IFERROR('Data Sheet'!B93,0) -> 88.78 | D37: =IFERROR('Data Sheet'!C93,0) -> 88.78 | E37: =IFERROR('Data Sheet'!D93,0) -> 88.78 | F37: =IFERROR('Data Sheet'!E93,0) -> 88.78 | G37: =IFERROR('Data Sheet'!F93,0) -> 88.78 | H37: =IFERROR('Data Sheet'!G93,0) -> 88.78 | I37: =IFERROR('Data Sheet'!H93,0) -> 88.78 | J37: =IFERROR('Data Sheet'!I93,0) -> 88.78 | ... L37: =IFERROR('Data Sheet'!K93,0) -> 88.78
B39: EPS | C39: =IFERROR(C34/C37,0) -> 7.8540212 | D39: =IFERROR(D34/D37,0) -> 12.411692 | E39: =IFERROR(E34/E37,0) -> 15.641473 | F39: =IFERROR(F34/F37,0) -> 16.816851 | G39: =IFERROR(G34/G37,0) -> 10.970939 | H39: =IFERROR(H34/H37,0) -> 24.757828 | I39: =IFERROR(I34/I37,0) -> 36.877675 | J39: =IFERROR(J34/J37,0) -> 39.378238 | ... L39: =IFERROR(L34/L37,0) -> 57.141248
B40: EPS growth % | C40: - | D40: =(D39/C39)-1 -> 0.58029773 | E40: =(E39/D39)-1 -> 0.26022089 | F40: =(F39/E39)-1 -> 0.075144925 | G40: =(G39/F39)-1 -> -0.34762224 | H40: =(H39/G39)-1 -> 1.2566735 | I40: =(I39/H39)-1 -> 0.48953594 | J40: =(J39/I39)-1 -> 0.067806964 | K40: =(K39/J39)-1 -> -0.045480549 | L40: =(L39/K39)-1 -> 0.52022775
B42: Dividend per Share | C42: =IFERROR('Data Sheet'!B31/Historical_FS!C37,0) -> 2.6000225 | D42: =IFERROR('Data Sheet'!C31/Historical_FS!D37,0) -> 3.7499437 | E42: =IFERROR('Data Sheet'!D31/Historical_FS!E37,0) -> 5 | F42: =IFERROR('Data Sheet'!E31/Historical_FS!F37,0) -> 4.0099121 | G42: =IFERROR('Data Sheet'!F31/Historical_FS!G37,0) -> 4.0099121 | H42: =IFERROR('Data Sheet'!G31/Historical_FS!H37,0) -> 7.5185853 | I42: =IFERROR('Data Sheet'!H31/Historical_FS!I37,0) -> 10.02478 | J42: =IFERROR('Data Sheet'!I31/Historical_FS!J37,0) -> 11.027258 | ... L42: =IFERROR('Data Sheet'!K31/Historical_FS!L37,0) -> 15.037171
B43: Dividend payout ratio | C43: =C42/C39 -> 0.33104348 | D43: =D42/D39 -> 0.30212994 | E43: =E42/E39 -> 0.31966298 | F43: =F42/F39 -> 0.23844608 | G43: =G42/G39 -> 0.36550308 | H43: =H42/H39 -> 0.30368517 | I43: =I42/I39 -> 0.27183873 | J43: =J42/J39 -> 0.28003432 | ... L43: =L42/L39 -> 0.26315789
B45: Retained Earnings | C45: =IFERROR(IF(C39>C42,1-C43,0),0) -> 0.66895652 | D45: =IFERROR(IF(D39>D42,1-D43,0),0) -> 0.69787006 | E45: =IFERROR(IF(E39>E42,1-E43,0),0) -> 0.68033702 | F45: =IFERROR(IF(F39>F42,1-F43,0),0) -> 0.76155392 | G45: =IFERROR(IF(G39>G42,1-G43,0),0) -> 0.63449692 | H45: =IFERROR(IF(H39>H42,1-H43,0),0) -> 0.69631483 | I45: =IFERROR(IF(I39>I42,1-I43,0),0) -> 0.72816127 | J45: =IFERROR(IF(J39>J42,1-J43,0),0) -> 0.71996568 | ... L45: =IFERROR(IF(L39>L42,1-L43,0),0) -> 0.73684211
B47: #Balance Sheet
B49: Equity Share Capital | C49: =IFERROR('Data Sheet'!B57,0) -> 88.78 | D49: =IFERROR('Data Sheet'!C57,0) -> 88.78 | E49: =IFERROR('Data Sheet'!D57,0) -> 88.78 | F49: =IFERROR('Data Sheet'!E57,0) -> 89 | G49: =IFERROR('Data Sheet'!F57,0) -> 89 | H49: =IFERROR('Data Sheet'!G57,0) -> 89 | I49: =IFERROR('Data Sheet'!H57,0) -> 89 | J49: =IFERROR('Data Sheet'!I57,0) -> 89 | ... L49: =IFERROR('Data Sheet'!K57,0) -> 89
B50: Reserves | C50: =IFERROR('Data Sheet'!B58,0) -> 4143.6 | D50: =IFERROR('Data Sheet'!C58,0) -> 5001.1 | E50: =IFERROR('Data Sheet'!D58,0) -> 5981.37 | F50: =IFERROR('Data Sheet'!E58,0) -> 6580 | G50: =IFERROR('Data Sheet'!F58,0) -> 7408 | H50: =IFERROR('Data Sheet'!G58,0) -> 9214 | I50: =IFERROR('Data Sheet'!H58,0) -> 11762 | J50: =IFERROR('Data Sheet'!I58,0) -> 9304 | ... L50: =IFERROR('Data Sheet'!K58,0) -> 15614
B51: Borrowings | C51: =IFERROR('Data Sheet'!B59,0) -> 1882.43 | D51: =IFERROR('Data Sheet'!C59,0) -> 1691.01 | E51: =IFERROR('Data Sheet'!D59,0) -> 2392.98 | F51: =IFERROR('Data Sheet'!E59,0) -> 3562 | G51: =IFERROR('Data Sheet'!F59,0) -> 5638 | H51: =IFERROR('Data Sheet'!G59,0) -> 7275 | I51: =IFERROR('Data Sheet'!H59,0) -> 9367 | J51: =IFERROR('Data Sheet'!I59,0) -> 15528 | ... L51: =IFERROR('Data Sheet'!K59,0) -> 30621
B52: Other Liabilities | C52: =IFERROR('Data Sheet'!B60,0) -> 2292.76 | D52: =IFERROR('Data Sheet'!C60,0) -> 2740.15 | E52: =IFERROR('Data Sheet'!D60,0) -> 3246.71 | F52: =IFERROR('Data Sheet'!E60,0) -> 3313 | G52: =IFERROR('Data Sheet'!F60,0) -> 3309 | H52: =IFERROR('Data Sheet'!G60,0) -> 4610 | I52: =IFERROR('Data Sheet'!H60,0) -> 5802 | J52: =IFERROR('Data Sheet'!I60,0) -> 6626 | ... L52: =IFERROR('Data Sheet'!K60,0) -> 14237
B53: Total Liabilities | C53: =IFERROR('Data Sheet'!B61,0) -> 8407.57 | D53: =IFERROR('Data Sheet'!C61,0) -> 9521.04 | E53: =IFERROR('Data Sheet'!D61,0) -> 11709.84 | F53: =IFERROR('Data Sheet'!E61,0) -> 13544 | G53: =IFERROR('Data Sheet'!F61,0) -> 16444 | H53: =IFERROR('Data Sheet'!G61,0) -> 21188 | I53: =IFERROR('Data Sheet'!H61,0) -> 27020 | J53: =IFERROR('Data Sheet'!I61,0) -> 31547 | ... L53: =IFERROR('Data Sheet'!K61,0) -> 60561
B55: Fixed Asset Net Block | C55: =IFERROR('Data Sheet'!B62,0) -> 1188.72 | D55: =IFERROR('Data Sheet'!C62,0) -> 1473.81 | E55: =IFERROR('Data Sheet'!D62,0) -> 1566.63 | F55: =IFERROR('Data Sheet'!E62,0) -> 2633 | G55: =IFERROR('Data Sheet'!F62,0) -> 2523 | H55: =IFERROR('Data Sheet'!G62,0) -> 2544 | I55: =IFERROR('Data Sheet'!H62,0) -> 2998 | J55: =IFERROR('Data Sheet'!I62,0) -> 3709 | ... L55: =IFERROR('Data Sheet'!K62,0) -> 6878
B56: Capital Work in Progress | C56: =IFERROR('Data Sheet'!B63,0) -> 152.07 | D56: =IFERROR('Data Sheet'!C63,0) -> 43.37 | E56: =IFERROR('Data Sheet'!D63,0) -> 31.77 | F56: =IFERROR('Data Sheet'!E63,0) -> 18 | G56: =IFERROR('Data Sheet'!F63,0) -> 32 | H56: =IFERROR('Data Sheet'!G63,0) -> 85 | I56: =IFERROR('Data Sheet'!H63,0) -> 144 | J56: =IFERROR('Data Sheet'!I63,0) -> 97 | ... L56: =IFERROR('Data Sheet'!K63,0) -> 163
B57: Investments | C57: =IFERROR('Data Sheet'!B64,0) -> 430.73 | D57: =IFERROR('Data Sheet'!C64,0) -> 35.99 | E57: =IFERROR('Data Sheet'!D64,0) -> 108.42 | F57: =IFERROR('Data Sheet'!E64,0) -> 158 | G57: =IFERROR('Data Sheet'!F64,0) -> 2824 | H57: =IFERROR('Data Sheet'!G64,0) -> 294 | I57: =IFERROR('Data Sheet'!H64,0) -> 2515 | J57: =IFERROR('Data Sheet'!I64,0) -> 2345 | ... L57: =IFERROR('Data Sheet'!K64,0) -> 3506
B58: Other Assets | C58: =IFERROR('Data Sheet'!B65-SUM('Data Sheet'!B67:B69),0) -> 723.78 | D58: =IFERROR('Data Sheet'!C65-SUM('Data Sheet'!C67:C69),0) -> 1129.43 | E58: =IFERROR('Data Sheet'!D65-SUM('Data Sheet'!D67:D69),0) -> 1477.27 | F58: =IFERROR('Data Sheet'!E65-SUM('Data Sheet'!E67:E69),0) -> 1939 | G58: =IFERROR('Data Sheet'!F65-SUM('Data Sheet'!F67:F69),0) -> 1731 | H58: =IFERROR('Data Sheet'!G65-SUM('Data Sheet'!G67:G69),0) -> 2518 | I58: =IFERROR('Data Sheet'!H65-SUM('Data Sheet'!H67:H69),0) -> 2762 | J58: =IFERROR('Data Sheet'!I65-SUM('Data Sheet'!I67:I69),0) -> 3801 | ... L58: =IFERROR('Data Sheet'!K65-SUM('Data Sheet'!K67:K69),0) -> 4438
B59: Total Non Current Assets | C59: =IFERROR(SUM(C55:C58),0) -> 2495.3 | D59: =IFERROR(SUM(D55:D58),0) -> 2682.6 | E59: =IFERROR(SUM(E55:E58),0) -> 3184.09 | F59: =IFERROR(SUM(F55:F58),0) -> 4748 | G59: =IFERROR(SUM(G55:G58),0) -> 7110 | H59: =IFERROR(SUM(H55:H58),0) -> 5441 | I59: =IFERROR(SUM(I55:I58),0) -> 8419 | J59: =IFERROR(SUM(J55:J58),0) -> 9952 | ... L59: =IFERROR(SUM(L55:L58),0) -> 14985
B61: Receivables | C61: =IFERROR('Data Sheet'!B67,0) -> 207.6 | D61: =IFERROR('Data Sheet'!C67,0) -> 295.69 | E61: =IFERROR('Data Sheet'!D67,0) -> 420.45 | F61: =IFERROR('Data Sheet'!E67,0) -> 312 | G61: =IFERROR('Data Sheet'!F67,0) -> 366 | H61: =IFERROR('Data Sheet'!G67,0) -> 565 | I61: =IFERROR('Data Sheet'!H67,0) -> 674 | J61: =IFERROR('Data Sheet'!I67,0) -> 1018 | ... L61: =IFERROR('Data Sheet'!K67,0) -> 916
B62: Inventory | C62: =IFERROR('Data Sheet'!B68,0) -> 4925.74 | D62: =IFERROR('Data Sheet'!C68,0) -> 5924.84 | E62: =IFERROR('Data Sheet'!D68,0) -> 7038.82 | F62: =IFERROR('Data Sheet'!E68,0) -> 8103 | G62: =IFERROR('Data Sheet'!F68,0) -> 8408 | H62: =IFERROR('Data Sheet'!G68,0) -> 13609 | I62: =IFERROR('Data Sheet'!H68,0) -> 16584 | J62: =IFERROR('Data Sheet'!I68,0) -> 19051 | ... L62: =IFERROR('Data Sheet'!K68,0) -> 42743
B63: Cash & Bank | C63: =IFERROR('Data Sheet'!B69,0) -> 778.93 | D63: =IFERROR('Data Sheet'!C69,0) -> 617.91 | E63: =IFERROR('Data Sheet'!D69,0) -> 1066.48 | F63: =IFERROR('Data Sheet'!E69,0) -> 381 | G63: =IFERROR('Data Sheet'!F69,0) -> 560 | H63: =IFERROR('Data Sheet'!G69,0) -> 1573 | I63: =IFERROR('Data Sheet'!H69,0) -> 1343 | J63: =IFERROR('Data Sheet'!I69,0) -> 1526 | ... L63: =IFERROR('Data Sheet'!K69,0) -> 1917
B64: Total Current Assets | C64: =IFERROR(SUM(C61:C63),0) -> 5912.27 | D64: =IFERROR(SUM(D61:D63),0) -> 6838.44 | E64: =IFERROR(SUM(E61:E63),0) -> 8525.75 | F64: =IFERROR(SUM(F61:F63),0) -> 8796 | G64: =IFERROR(SUM(G61:G63),0) -> 9334 | H64: =IFERROR(SUM(H61:H63),0) -> 15747 | I64: =IFERROR(SUM(I61:I63),0) -> 18601 | J64: =IFERROR(SUM(J61:J63),0) -> 21595 | ... L64: =IFERROR(SUM(L61:L63),0) -> 45576
B66: Total Assets | C66: =IFERROR(SUM(C59,C64),0) -> 8407.57 | D66: =IFERROR(SUM(D59,D64),0) -> 9521.04 | E66: =IFERROR(SUM(E59,E64),0) -> 11709.84 | F66: =IFERROR(SUM(F59,F64),0) -> 13544 | G66: =IFERROR(SUM(G59,G64),0) -> 16444 | H66: =IFERROR(SUM(H59,H64),0) -> 21188 | I66: =IFERROR(SUM(I59,I64),0) -> 27020 | J66: =IFERROR(SUM(J59,J64),0) -> 31547 | ... L66: =IFERROR(SUM(L59,L64),0) -> 60561
B68: Check | C68: =C66=C53 -> TRUE | D68: =D66=D53 -> TRUE | E68: =E66=E53 -> TRUE | F68: =F66=F53 -> TRUE | G68: =G66=G53 -> TRUE | H68: =H66=H53 -> TRUE | I68: =I66=I53 -> TRUE | J68: =J66=J53 -> TRUE | ... L68: =L66=L53 -> TRUE
B70: #Cash Flow Statements
B72: Operating Activities
B73: Profit from operations | C73: =IFERROR('Cash Flow Data'!E6,0) -> 1073 | D73: =IFERROR('Cash Flow Data'!F6,0) -> 1642 | E73: =IFERROR('Cash Flow Data'!G6,0) -> 2183 | F73: =IFERROR('Cash Flow Data'!H6,0) -> 2481 | G73: =IFERROR('Cash Flow Data'!I6,0) -> 1789 | H73: =IFERROR('Cash Flow Data'!J6,0) -> 3298 | I73: =IFERROR('Cash Flow Data'!K6,0) -> 4937 | J73: =IFERROR('Cash Flow Data'!L6,0) -> 5404 | ... L73: =IFERROR('Cash Flow Data'!N6,0) -> 8447
B74: Receivables | C74: =IFERROR('Cash Flow Data'!E7,0) -> -12 | D74: =IFERROR('Cash Flow Data'!F7,0) -> -90 | E74: =IFERROR('Cash Flow Data'!G7,0) -> -139 | F74: =IFERROR('Cash Flow Data'!H7,0) -> 109 | G74: =IFERROR('Cash Flow Data'!I7,0) -> -59 | H74: =IFERROR('Cash Flow Data'!J7,0) -> -207 | I74: =IFERROR('Cash Flow Data'!K7,0) -> -112 | J74: =IFERROR('Cash Flow Data'!L7,0) -> -348 | ... L74: =IFERROR('Cash Flow Data'!N7,0) -> 210
B75: Inventory | C75: =IFERROR('Cash Flow Data'!E8,0) -> -448 | D75: =IFERROR('Cash Flow Data'!F8,0) -> -996 | E75: =IFERROR('Cash Flow Data'!G8,0) -> -1120 | F75: =IFERROR('Cash Flow Data'!H8,0) -> -1057 | G75: =IFERROR('Cash Flow Data'!I8,0) -> -316 | H75: =IFERROR('Cash Flow Data'!J8,0) -> -5199 | I75: =IFERROR('Cash Flow Data'!K8,0) -> -2977 | J75: =IFERROR('Cash Flow Data'!L8,0) -> -2462 | ... L75: =IFERROR('Cash Flow Data'!N8,0) -> -11592
B76: Payables | C76: =IFERROR('Cash Flow Data'!E9,0) -> 238 | D76: =IFERROR('Cash Flow Data'!F9,0) -> 95 | E76: =IFERROR('Cash Flow Data'!G9,0) -> 32 | F76: =IFERROR('Cash Flow Data'!H9,0) -> -310 | G76: =IFERROR('Cash Flow Data'!I9,0) -> 195 | H76: =IFERROR('Cash Flow Data'!J9,0) -> 504 | I76: =IFERROR('Cash Flow Data'!K9,0) -> -89 | J76: =IFERROR('Cash Flow Data'!L9,0) -> 196 | ... L76: =IFERROR('Cash Flow Data'!N9,0) -> 472
B77: Loans Advances | C77: =IFERROR('Cash Flow Data'!E10,0) -> 0 | D77: =IFERROR('Cash Flow Data'!F10,0) -> 3 | E77: =IFERROR('Cash Flow Data'!G10,0) -> -24 | F77: =IFERROR('Cash Flow Data'!H10,0) -> -20 | G77: =IFERROR('Cash Flow Data'!I10,0) -> -8 | H77: =IFERROR('Cash Flow Data'!J10,0) -> -3 | I77: =IFERROR('Cash Flow Data'!K10,0) -> -18 | J77: =IFERROR('Cash Flow Data'!L10,0) -> -21 | ... L77: =IFERROR('Cash Flow Data'!N10,0) -> -8
B78: Operating borrowings | C78: =IFERROR('Cash Flow Data'!E11,0) -> 763 | D78: =IFERROR('Cash Flow Data'!F11,0) -> -270 | E78: =IFERROR('Cash Flow Data'!G11,0) -> 741 | F78: =IFERROR('Cash Flow Data'!H11,0) -> -768 | G78: =IFERROR('Cash Flow Data'!I11,0) -> 2625 | H78: =IFERROR('Cash Flow Data'!J11,0) -> 1188 | I78: =IFERROR('Cash Flow Data'!K11,0) -> -99 | J78: =IFERROR('Cash Flow Data'!L11,0) -> 42 | ... L78: =IFERROR('Cash Flow Data'!N11,0) -> 7304
B79: Other WC items | C79: =IFERROR('Cash Flow Data'!E12,0) -> 375 | D79: =IFERROR('Cash Flow Data'!F12,0) -> 22 | E79: =IFERROR('Cash Flow Data'!G12,0) -> 206 | F79: =IFERROR('Cash Flow Data'!H12,0) -> -226 | G79: =IFERROR('Cash Flow Data'!I12,0) -> 184 | H79: =IFERROR('Cash Flow Data'!J12,0) -> 497 | I79: =IFERROR('Cash Flow Data'!K12,0) -> 882 | J79: =IFERROR('Cash Flow Data'!L12,0) -> 57 | ... L79: =IFERROR('Cash Flow Data'!N12,0) -> 2494
B80: Working capital changes | C80: =IFERROR('Cash Flow Data'!E13,0) -> 916 | D80: =IFERROR('Cash Flow Data'!F13,0) -> -1237 | E80: =IFERROR('Cash Flow Data'!G13,0) -> -304 | F80: =IFERROR('Cash Flow Data'!H13,0) -> -2272 | G80: =IFERROR('Cash Flow Data'!I13,0) -> 2621 | H80: =IFERROR('Cash Flow Data'!J13,0) -> -3220 | I80: =IFERROR('Cash Flow Data'!K13,0) -> -2413 | J80: =IFERROR('Cash Flow Data'!L13,0) -> -2536 | ... L80: =IFERROR('Cash Flow Data'!N13,0) -> -1120
B81: Direct taxes | C81: =IFERROR('Cash Flow Data'!E14,0) -> -277 | D81: =IFERROR('Cash Flow Data'!F14,0) -> -456 | E81: =IFERROR('Cash Flow Data'!G14,0) -> -636 | F81: =IFERROR('Cash Flow Data'!H14,0) -> -557 | G81: =IFERROR('Cash Flow Data'!I14,0) -> -271 | H81: =IFERROR('Cash Flow Data'!J14,0) -> -802 | I81: =IFERROR('Cash Flow Data'!K14,0) -> -1154 | J81: =IFERROR('Cash Flow Data'!L14,0) -> -1173 | ... L81: =IFERROR('Cash Flow Data'!N14,0) -> -1737
B82: Cash from Operating Activities | C82: =SUM(C73:C81) -> 2628 | D82: =SUM(D73:D81) -> -1287 | E82: =SUM(E73:E81) -> 939 | F82: =SUM(F73:F81) -> -2620 | G82: =SUM(G73:G81) -> 6760 | H82: =SUM(H73:H81) -> -3944 | I82: =SUM(I73:I81) -> -1043 | J82: =SUM(J73:J81) -> -841 | ... L82: =SUM(L73:L81) -> 4470
B84: Investing Activities
B85: Fixed assets purchased | C85: =IFERROR('Cash Flow Data'!E16,0) -> -256 | D85: =IFERROR('Cash Flow Data'!F16,0) -> -305 | E85: =IFERROR('Cash Flow Data'!G16,0) -> -265 | F85: =IFERROR('Cash Flow Data'!H16,0) -> -355 | G85: =IFERROR('Cash Flow Data'!I16,0) -> -146 | H85: =IFERROR('Cash Flow Data'!J16,0) -> -224 | I85: =IFERROR('Cash Flow Data'!K16,0) -> -432 | J85: =IFERROR('Cash Flow Data'!L16,0) -> -691 | ... L85: =IFERROR('Cash Flow Data'!N16,0) -> -902
B86: Fixed assets sold | C86: =IFERROR('Cash Flow Data'!E17,0) -> 5 | D86: =IFERROR('Cash Flow Data'!F17,0) -> 6 | E86: =IFERROR('Cash Flow Data'!G17,0) -> 1 | F86: =IFERROR('Cash Flow Data'!H17,0) -> 10 | G86: =IFERROR('Cash Flow Data'!I17,0) -> 7 | H86: =IFERROR('Cash Flow Data'!J17,0) -> 8 | I86: =IFERROR('Cash Flow Data'!K17,0) -> 12 | J86: =IFERROR('Cash Flow Data'!L17,0) -> 20 | ... L86: =IFERROR('Cash Flow Data'!N17,0) -> 25
B87: Investments purchased | C87: =IFERROR('Cash Flow Data'!E18,0) -> -325 | D87: =IFERROR('Cash Flow Data'!F18,0) -> 0 | E87: =IFERROR('Cash Flow Data'!G18,0) -> -36 | F87: =IFERROR('Cash Flow Data'!H18,0) -> -13 | G87: =IFERROR('Cash Flow Data'!I18,0) -> -2656 | H87: =IFERROR('Cash Flow Data'!J18,0) -> -253 | I87: =IFERROR('Cash Flow Data'!K18,0) -> -2104 | J87: =IFERROR('Cash Flow Data'!L18,0) -> -21893 | ... L87: =IFERROR('Cash Flow Data'!N18,0) -> -22035
B88: Investments sold | C88: =IFERROR('Cash Flow Data'!E19,0) -> 0 | D88: =IFERROR('Cash Flow Data'!F19,0) -> 412 | E88: =IFERROR('Cash Flow Data'!G19,0) -> 18 | F88: =IFERROR('Cash Flow Data'!H19,0) -> 0 | G88: =IFERROR('Cash Flow Data'!I19,0) -> 43 | H88: =IFERROR('Cash Flow Data'!J19,0) -> 2870 | I88: =IFERROR('Cash Flow Data'!K19,0) -> 0 | J88: =IFERROR('Cash Flow Data'!L19,0) -> 22213 | ... L88: =IFERROR('Cash Flow Data'!N19,0) -> 20797
B89: Interest received | C89: =IFERROR('Cash Flow Data'!E20,0) -> 41 | D89: =IFERROR('Cash Flow Data'!F20,0) -> 64 | E89: =IFERROR('Cash Flow Data'!G20,0) -> 85 | F89: =IFERROR('Cash Flow Data'!H20,0) -> 73 | G89: =IFERROR('Cash Flow Data'!I20,0) -> 49 | H89: =IFERROR('Cash Flow Data'!J20,0) -> 56 | I89: =IFERROR('Cash Flow Data'!K20,0) -> 143 | J89: =IFERROR('Cash Flow Data'!L20,0) -> 249 | ... L89: =IFERROR('Cash Flow Data'!N20,0) -> 227
B90: Invest in subsidiaries | C90: =IFERROR('Cash Flow Data'!E21,0) -> 0 | D90: =IFERROR('Cash Flow Data'!F21,0) -> 0 | E90: =IFERROR('Cash Flow Data'!G21,0) -> 0 | F90: =IFERROR('Cash Flow Data'!H21,0) -> -39 | G90: =IFERROR('Cash Flow Data'!I21,0) -> 0 | H90: =IFERROR('Cash Flow Data'!J21,0) -> 0 | I90: =IFERROR('Cash Flow Data'!K21,0) -> 0 | J90: =IFERROR('Cash Flow Data'!L21,0) -> 0 | ... L90: =IFERROR('Cash Flow Data'!N21,0) -> 0
B91: Investment in group cos | C91: =IFERROR('Cash Flow Data'!E22,0) -> 0 | D91: =IFERROR('Cash Flow Data'!F22,0) -> 0 | E91: =IFERROR('Cash Flow Data'!G22,0) -> 0 | F91: =IFERROR('Cash Flow Data'!H22,0) -> 0 | G91: =IFERROR('Cash Flow Data'!I22,0) -> 0 | H91: =IFERROR('Cash Flow Data'!J22,0) -> 0 | I91: =IFERROR('Cash Flow Data'!K22,0) -> 0 | J91: =IFERROR('Cash Flow Data'!L22,0) -> 0 | ... L91: =IFERROR('Cash Flow Data'!N22,0) -> 0
B92: Acquisition of companies | C92: =IFERROR('Cash Flow Data'!E23,0) -> -385 | D92: =IFERROR('Cash Flow Data'!F23,0) -> 0 | E92: =IFERROR('Cash Flow Data'!G23,0) -> 0 | F92: =IFERROR('Cash Flow Data'!H23,0) -> 0 | G92: =IFERROR('Cash Flow Data'!I23,0) -> 0 | H92: =IFERROR('Cash Flow Data'!J23,0) -> 0 | I92: =IFERROR('Cash Flow Data'!K23,0) -> 0 | J92: =IFERROR('Cash Flow Data'!L23,0) -> 0 | ... L92: =IFERROR('Cash Flow Data'!N23,0) -> 0
B93: Inter corporate deposits | C93: =IFERROR('Cash Flow Data'!E24,0) -> 5 | D93: =IFERROR('Cash Flow Data'!F24,0) -> -35 | E93: =IFERROR('Cash Flow Data'!G24,0) -> -115 | F93: =IFERROR('Cash Flow Data'!H24,0) -> 200 | G93: =IFERROR('Cash Flow Data'!I24,0) -> -50 | H93: =IFERROR('Cash Flow Data'!J24,0) -> -344 | I93: =IFERROR('Cash Flow Data'!K24,0) -> 294 | J93: =IFERROR('Cash Flow Data'!L24,0) -> -143 | ... L93: =IFERROR('Cash Flow Data'!N24,0) -> 0
B94: Other investing items | C94: =IFERROR('Cash Flow Data'!E25,0) -> -38 | D94: =IFERROR('Cash Flow Data'!F25,0) -> -43 | E94: =IFERROR('Cash Flow Data'!G25,0) -> -485 | F94: =IFERROR('Cash Flow Data'!H25,0) -> 359 | G94: =IFERROR('Cash Flow Data'!I25,0) -> -46 | H94: =IFERROR('Cash Flow Data'!J25,0) -> -948 | I94: =IFERROR('Cash Flow Data'!K25,0) -> 273 | J94: =IFERROR('Cash Flow Data'!L25,0) -> 56 | ... L94: =IFERROR('Cash Flow Data'!N25,0) -> -1077
B95: Cash from Investing Activities | C95: =SUM(C85:C94) -> -953 | D95: =SUM(D85:D94) -> 99 | E95: =SUM(E85:E94) -> -797 | F95: =SUM(F85:F94) -> 235 | G95: =SUM(G85:G94) -> -2799 | H95: =SUM(H85:H94) -> 1165 | I95: =SUM(I85:I94) -> -1814 | J95: =SUM(J85:J94) -> -189 | ... L95: =SUM(L85:L94) -> -2965
B97: Financing Activities
B98: Proceeds from borrowings | C98: =IFERROR('Cash Flow Data'!E27,0) -> 0 | D98: =IFERROR('Cash Flow Data'!F27,0) -> 0 | E98: =IFERROR('Cash Flow Data'!G27,0) -> 0 | F98: =IFERROR('Cash Flow Data'!H27,0) -> 693 | G98: =IFERROR('Cash Flow Data'!I27,0) -> 0 | H98: =IFERROR('Cash Flow Data'!J27,0) -> 349 | I98: =IFERROR('Cash Flow Data'!K27,0) -> 1684 | J98: =IFERROR('Cash Flow Data'!L27,0) -> 5629 | ... L98: =IFERROR('Cash Flow Data'!N27,0) -> 3314
B99: Repayment of borrowings | C99: =IFERROR('Cash Flow Data'!E28,0) -> 0 | D99: =IFERROR('Cash Flow Data'!F28,0) -> 0 | E99: =IFERROR('Cash Flow Data'!G28,0) -> -39 | F99: =IFERROR('Cash Flow Data'!H28,0) -> 0 | G99: =IFERROR('Cash Flow Data'!I28,0) -> -562 | H99: =IFERROR('Cash Flow Data'!J28,0) -> -7 | I99: =IFERROR('Cash Flow Data'!K28,0) -> -7 | J99: =IFERROR('Cash Flow Data'!L28,0) -> 0 | ... L99: =IFERROR('Cash Flow Data'!N28,0) -> -2632
B100: Interest paid fin | C100: =IFERROR('Cash Flow Data'!E29,0) -> -38 | D100: =IFERROR('Cash Flow Data'!F29,0) -> -54 | E100: =IFERROR('Cash Flow Data'!G29,0) -> -53 | F100: =IFERROR('Cash Flow Data'!H29,0) -> -399 | G100: =IFERROR('Cash Flow Data'!I29,0) -> -317 | H100: =IFERROR('Cash Flow Data'!J29,0) -> -218 | I100: =IFERROR('Cash Flow Data'!K29,0) -> -300 | J100: =IFERROR('Cash Flow Data'!L29,0) -> -619 | ... L100: =IFERROR('Cash Flow Data'!N29,0) -> -1000
B101: Dividends paid | C101: =IFERROR('Cash Flow Data'!E30,0) -> -4 | D101: =IFERROR('Cash Flow Data'!F30,0) -> -277 | E101: =IFERROR('Cash Flow Data'!G30,0) -> -397 | F101: =IFERROR('Cash Flow Data'!H30,0) -> -536 | G101: =IFERROR('Cash Flow Data'!I30,0) -> -355 | H101: =IFERROR('Cash Flow Data'!J30,0) -> -355 | I101: =IFERROR('Cash Flow Data'!K30,0) -> -666 | J101: =IFERROR('Cash Flow Data'!L30,0) -> -888 | ... L101: =IFERROR('Cash Flow Data'!N30,0) -> -976
B102: Financial liabilities | C102: =IFERROR('Cash Flow Data'!E31,0) -> 0 | D102: =IFERROR('Cash Flow Data'!F31,0) -> 0 | E102: =IFERROR('Cash Flow Data'!G31,0) -> 0 | F102: =IFERROR('Cash Flow Data'!H31,0) -> 0 | G102: =IFERROR('Cash Flow Data'!I31,0) -> 0 | H102: =IFERROR('Cash Flow Data'!J31,0) -> -172 | I102: =IFERROR('Cash Flow Data'!K31,0) -> -254 | J102: =IFERROR('Cash Flow Data'!L31,0) -> -318 | ... L102: =IFERROR('Cash Flow Data'!N31,0) -> -865
B103: Other financing items | C103: =IFERROR('Cash Flow Data'!E32,0) -> -124 | D103: =IFERROR('Cash Flow Data'!F32,0) -> 79 | E103: =IFERROR('Cash Flow Data'!G32,0) -> 0 | F103: =IFERROR('Cash Flow Data'!H32,0) -> 0 | G103: =IFERROR('Cash Flow Data'!I32,0) -> 0 | H103: =IFERROR('Cash Flow Data'!J32,0) -> 0 | I103: =IFERROR('Cash Flow Data'!K32,0) -> 0 | J103: =IFERROR('Cash Flow Data'!L32,0) -> -5133 | ... L103: =IFERROR('Cash Flow Data'!N32,0) -> 0
B104: Cash from Financing Activities | C104: =SUM(C98:C103) -> -166 | D104: =SUM(D98:D103) -> -252 | E104: =SUM(E98:E103) -> -489 | F104: =SUM(F98:F103) -> -242 | G104: =SUM(G98:G103) -> -1234 | H104: =SUM(H98:H103) -> -403 | I104: =SUM(I98:I103) -> 457 | J104: =SUM(J98:J103) -> -1329 | ... L104: =SUM(L98:L103) -> -2159
B106: Net Cash Flow | C106: =IFERROR(SUM(C82,C95,C104),0) -> 1509 | D106: =IFERROR(SUM(D82,D95,D104),0) -> -1440 | E106: =IFERROR(SUM(E82,E95,E104),0) -> -347 | F106: =IFERROR(SUM(F82,F95,F104),0) -> -2627 | G106: =IFERROR(SUM(G82,G95,G104),0) -> 2727 | H106: =IFERROR(SUM(H82,H95,H104),0) -> -3182 | I106: =IFERROR(SUM(I82,I95,I104),0) -> -2400 | J106: =IFERROR(SUM(J82,J95,J104),0) -> -2359 | ... L106: =IFERROR(SUM(L82,L95,L104),0) -> -654

Sheet Supporting Schedules

Sheet Du Pont Analysis
B3: ='Data Sheet'!B1 -> TITAN COMPANY LTD
B4: TITAN I BSE:500114
B5: =CONCATENATE(" ","INR "&'Data Sheet'!B8) -> INR 4515.7
B6: 52 week (High- 5187 & Low- 3500)
B8: About The Company
B9: Titan Company Ltd is among India’s most respected lifestyle companies. It has established leadership positions in the Watches, Jewellery and Eyewear categories led by its trusted brands and differentiated customer experience. It was founded in 1984 as a joint-venture between TATA Group and Tamilnadu Industrial Development Corporation (TIDCO).
B11: Financial Summary
B36: Dupont Analysis- Return on Equity & Return on Asset
B38: Return on Equity
C39: =Historical_FS!F3 -> 43921 | D39: =Historical_FS!G3 -> 44286 | E39: =Historical_FS!H3 -> 44651 | F39: =Historical_FS!I3 -> 45016 | G39: =Historical_FS!J3 -> 45382 | H39: =Historical_FS!K3 -> 45747 | I39: =Historical_FS!L3 -> 46112
B40: Net Profit | C40: ='Data Sheet'!E30 -> 1501 | D40: ='Data Sheet'!F30 -> 973 | E40: ='Data Sheet'!G30 -> 2173 | F40: ='Data Sheet'!H30 -> 3250 | G40: ='Data Sheet'!I30 -> 3496 | H40: ='Data Sheet'!J30 -> 3337 | I40: ='Data Sheet'!K30 -> 5073
B41: Average Shareholder Equity | C41: =(('Data Sheet'!E57+'Data Sheet'!E58)+('Data Sheet'!D57+'Data Sheet'!D58))/2 -> 6369.575 | D41: =(('Data Sheet'!F57+'Data Sheet'!F58)+('Data Sheet'!E57+'Data Sheet'!E58))/2 -> 7083 | E41: =(('Data Sheet'!G57+'Data Sheet'!G58)+('Data Sheet'!F57+'Data Sheet'!F58))/2 -> 8400 | F41: =(('Data Sheet'!H57+'Data Sheet'!H58)+('Data Sheet'!G57+'Data Sheet'!G58))/2 -> 10577 | G41: =(('Data Sheet'!I57+'Data Sheet'!I58)+('Data Sheet'!H57+'Data Sheet'!H58))/2 -> 10622 | H41: =(('Data Sheet'!J57+'Data Sheet'!J58)+('Data Sheet'!I57+'Data Sheet'!I58))/2 -> 10508.5 | I41: =(('Data Sheet'!K57+'Data Sheet'!K58)+('Data Sheet'!J57+'Data Sheet'!J58))/2 -> 13663.5
B42: Return on Equity | C42: =C40/C41 -> 0.23565152 | D42: =D40/D41 -> 0.13737117 | E42: =E40/E41 -> 0.25869048 | F42: =F40/F41 -> 0.30727049 | G42: =G40/G41 -> 0.32912822 | H42: =H40/H41 -> 0.31755246 | I42: =I40/I41 -> 0.37128115
B44: ROE- DuPont Equation
C45: =C39 -> 43921 | D45: =D39 -> 44286 | E45: =E39 -> 44651 | F45: =F39 -> 45016 | G45: =G39 -> 45382 | H45: =H39 -> 45747 | I45: =I39 -> 46112
B46: Net Profit | C46: =C40 -> 1501 | D46: =D40 -> 973 | E46: =E40 -> 2173 | F46: =F40 -> 3250 | G46: =G40 -> 3496 | H46: =H40 -> 3337 | I46: =I40 -> 5073
B47: Revenue | C47: ='Data Sheet'!E17 -> 21052 | D47: ='Data Sheet'!F17 -> 21644 | E47: ='Data Sheet'!G17 -> 28799 | F47: ='Data Sheet'!H17 -> 40575 | G47: ='Data Sheet'!I17 -> 51084 | H47: ='Data Sheet'!J17 -> 60456 | I47: ='Data Sheet'!K17 -> 87584
B48: Net Profit Margin (A) | C48: =C46/C47 -> 0.071299639 | D48: =D46/D47 -> 0.044954722 | E48: =E46/E47 -> 0.075454009 | F48: =F46/F47 -> 0.080098583 | G48: =G46/G47 -> 0.068436301 | H48: =H46/H47 -> 0.055197168 | I48: =I46/I47 -> 0.057921538
B50: Revenue | C50: =C47 -> 21052 | D50: =D47 -> 21644 | E50: =E47 -> 28799 | F50: =F47 -> 40575 | G50: =G47 -> 51084 | H50: =H47 -> 60456 | I50: =I47 -> 87584
B51: Average Total Assets | C51: =('Data Sheet'!E66+'Data Sheet'!D66)/2 -> 12626.92 | D51: =('Data Sheet'!F66+'Data Sheet'!E66)/2 -> 14994 | E51: =('Data Sheet'!G66+'Data Sheet'!F66)/2 -> 18816 | F51: =('Data Sheet'!H66+'Data Sheet'!G66)/2 -> 24104 | G51: =('Data Sheet'!I66+'Data Sheet'!H66)/2 -> 29283.5 | H51: =('Data Sheet'!J66+'Data Sheet'!I66)/2 -> 36096 | I51: =('Data Sheet'!K66+'Data Sheet'!J66)/2 -> 50603
B52: Asset Turnover Ratio (B) | C52: =C50/C51 -> 1.6672316 | D52: =D50/D51 -> 1.4435107 | E52: =E50/E51 -> 1.5305591 | F52: =F50/F51 -> 1.6833306 | G52: =G50/G51 -> 1.7444636 | H52: =H50/H51 -> 1.674867 | I52: =I50/I51 -> 1.7308065
B54: =B51 -> Average Total Assets | C54: =C51 -> 12626.92 | D54: =D51 -> 14994 | E54: =E51 -> 18816 | F54: =F51 -> 24104 | G54: =G51 -> 29283.5 | H54: =H51 -> 36096 | I54: =I51 -> 50603
B55: =B41 -> Average Shareholder Equity | C55: =C41 -> 6369.575 | D55: =D41 -> 7083 | E55: =E41 -> 8400 | F55: =F41 -> 10577 | G55: =G41 -> 10622 | H55: =H41 -> 10508.5 | I55: =I41 -> 13663.5
B56: Financial Leverage (C) | C56: =C54/C55 -> 1.9823803 | D56: =D54/D55 -> 2.1168996 | E56: =E54/E55 -> 2.24 | F56: =F54/F55 -> 2.2789071 | G56: =G54/G55 -> 2.7568725 | H56: =H54/H55 -> 3.4349336 | I56: =I54/I55 -> 3.7035167
B58: Return on Equity (A*B*C) | C58: =C48*C52*C56 -> 0.23565152 | D58: =D48*D52*D56 -> 0.13737117 | E58: =E48*E52*E56 -> 0.25869048 | F58: =F48*F52*F56 -> 0.30727049 | G58: =G48*G52*G56 -> 0.32912822 | H58: =H48*H52*H56 -> 0.31755246 | I58: =I48*I52*I56 -> 0.37128115
B60: Return on Asset
C61: =C39 -> 43921 | D61: =D39 -> 44286 | E61: =E39 -> 44651 | F61: =F39 -> 45016 | G61: =G39 -> 45382 | H61: =H39 -> 45747 | I61: =I39 -> 46112
B62: Net Profit | C62: =C46 -> 1501 | D62: =D46 -> 973 | E62: =E46 -> 2173 | F62: =F46 -> 3250 | G62: =G46 -> 3496 | H62: =H46 -> 3337 | I62: =I46 -> 5073
B63: Average Total Asset | C63: =C54 -> 12626.92 | D63: =D54 -> 14994 | E63: =E54 -> 18816 | F63: =F54 -> 24104 | G63: =G54 -> 29283.5 | H63: =H54 -> 36096 | I63: =I54 -> 50603
B64: Return on Asset | C64: =C62/C63 -> 0.11887301 | D64: =D62/D63 -> 0.064892624 | E64: =E62/E63 -> 0.11548682 | F64: =F62/F63 -> 0.13483239 | G64: =G62/G63 -> 0.11938464 | H64: =H62/H63 -> 0.092447917 | I64: =I62/I63 -> 0.10025097
B66: ROA- DuPont Equation
C67: =C45 -> 43921 | D67: =D45 -> 44286 | E67: =E45 -> 44651 | F67: =F45 -> 45016 | G67: =G45 -> 45382 | H67: =H45 -> 45747 | I67: =I45 -> 46112
B68: Net Profit | C68: =C46 -> 1501 | D68: =D46 -> 973 | E68: =E46 -> 2173 | F68: =F46 -> 3250 | G68: =G46 -> 3496 | H68: =H46 -> 3337 | I68: =I46 -> 5073
B69: Revenue | C69: =C50 -> 21052 | D69: =D50 -> 21644 | E69: =E50 -> 28799 | F69: =F50 -> 40575 | G69: =G50 -> 51084 | H69: =H50 -> 60456 | I69: =I50 -> 87584
B70: =B48 -> Net Profit Margin (A) | C70: =C68/C69 -> 0.071299639 | D70: =D68/D69 -> 0.044954722 | E70: =E68/E69 -> 0.075454009 | F70: =F68/F69 -> 0.080098583 | G70: =G68/G69 -> 0.068436301 | H70: =H68/H69 -> 0.055197168 | I70: =I68/I69 -> 0.057921538
B72: Revenue | C72: =C50 -> 21052 | D72: =D50 -> 21644 | E72: =E50 -> 28799 | F72: =F50 -> 40575 | G72: =G50 -> 51084 | H72: =H50 -> 60456 | I72: =I50 -> 87584
B73: Average Total Assets | C73: =C63 -> 12626.92 | D73: =D63 -> 14994 | E73: =E63 -> 18816 | F73: =F63 -> 24104 | G73: =G63 -> 29283.5 | H73: =H63 -> 36096 | I73: =I63 -> 50603
B74: Asset Turnover Ratio (B) | C74: =C72/C73 -> 1.6672316 | D74: =D72/D73 -> 1.4435107 | E74: =E72/E73 -> 1.5305591 | F74: =F72/F73 -> 1.6833306 | G74: =G72/G73 -> 1.7444636 | H74: =H72/H73 -> 1.674867 | I74: =I72/I73 -> 1.7308065
B76: Return on Asset (A*B) | C76: =C70*C74 -> 0.11887301 | D76: =D70*D74 -> 0.064892624 | E76: =E70*E74 -> 0.11548682 | F76: =F70*F74 -> 0.13483239 | G76: =G70*G74 -> 0.11938464 | H76: =H70*H74 -> 0.092447917 | I76: =I70*I74 -> 0.10025097
B93: Disclamer: this project is only for educational purpose

Sheet Altman Z score
B3: ='Data Sheet'!B1 -> TITAN COMPANY LTD
B4: TITAN I BSE:500114
B5: =CONCATENATE(" ","INR "&'Data Sheet'!B8) -> INR 4515.7
B6: 52 week (High- 5187 & Low- 3500)
B9: Financial Summary
B33: Altman Z score Analysis Calculation
B35: 1. Working Capital/ Total Assets
C36: =Historical_FS!F3 -> 43921 | D36: =Historical_FS!G3 -> 44286 | E36: =Historical_FS!H3 -> 44651 | F36: =Historical_FS!I3 -> 45016 | G36: =Historical_FS!J3 -> 45382 | H36: =Historical_FS!K3 -> 45747 | I36: =Historical_FS!L3 -> 46112
B37: Working Capital | C37: ='Data Sheet'!E65-'Data Sheet'!E60 -> 7422 | D37: ='Data Sheet'!F65-'Data Sheet'!F60 -> 7756 | E37: ='Data Sheet'!G65-'Data Sheet'!G60 -> 13655 | F37: ='Data Sheet'!H65-'Data Sheet'!H60 -> 15561 | G37: ='Data Sheet'!I65-'Data Sheet'!I60 -> 18770 | H37: ='Data Sheet'!J65-'Data Sheet'!J60 -> 26246 | I37: ='Data Sheet'!K65-'Data Sheet'!K60 -> 35777
B38: Total Assets | C38: ='Data Sheet'!E66 -> 13544 | D38: ='Data Sheet'!F66 -> 16444 | E38: ='Data Sheet'!G66 -> 21188 | F38: ='Data Sheet'!H66 -> 27020 | G38: ='Data Sheet'!I66 -> 31547 | H38: ='Data Sheet'!J66 -> 40645 | I38: ='Data Sheet'!K66 -> 60561
B39: Working Capital/ Total Assets (A) | C39: =C37/C38 -> 0.54799173 | D39: =D37/D38 -> 0.4716614 | E39: =E37/E38 -> 0.64446857 | F39: =F37/F38 -> 0.57590674 | G39: =G37/G38 -> 0.59498526 | H39: =H37/H38 -> 0.64573748 | I39: =I37/I38 -> 0.59075973
B41: 2. Retained Earnings/ Total Assets
C42: =C36 -> 43921 | D42: =D36 -> 44286 | E42: =E36 -> 44651 | F42: =F36 -> 45016 | G42: =G36 -> 45382 | H42: =H36 -> 45747 | I42: =I36 -> 46112
B43: Retained Earnings | C43: ='Data Sheet'!E58 -> 6580 | D43: ='Data Sheet'!F58 -> 7408 | E43: ='Data Sheet'!G58 -> 9214 | F43: ='Data Sheet'!H58 -> 11762 | G43: ='Data Sheet'!I58 -> 9304 | H43: ='Data Sheet'!J58 -> 11535 | I43: ='Data Sheet'!K58 -> 15614
B44: Total Assets | C44: =C38 -> 13544 | D44: =D38 -> 16444 | E44: =E38 -> 21188 | F44: =F38 -> 27020 | G44: =G38 -> 31547 | H44: =H38 -> 40645 | I44: =I38 -> 60561
B45: Retained Earnings/ Total Assets (B) | C45: =C43/C44 -> 0.48582398 | D45: =D43/D44 -> 0.45049866 | E45: =E43/E44 -> 0.43486879 | F45: =F43/F44 -> 0.43530718 | G45: =G43/G44 -> 0.29492503 | H45: =H43/H44 -> 0.28379875 | I45: =I43/I44 -> 0.25782269
B47: 3. EBIT/ Total Assets
C48: =C42 -> 43921 | D48: =D42 -> 44286 | E48: =E42 -> 44651 | F48: =F42 -> 45016 | G48: =G42 -> 45382 | H48: =H42 -> 45747 | I48: =I42 -> 46112
B49: EBIT | C49: =Historical_FS!F28+Historical_FS!F22 -> 2268 | D49: =Historical_FS!G28+Historical_FS!G22 -> 1530 | E49: =Historical_FS!H28+Historical_FS!H22 -> 3122 | F49: =Historical_FS!I28+Historical_FS!I22 -> 4747 | G49: =Historical_FS!J28+Historical_FS!J22 -> 5242 | H49: =Historical_FS!K28+Historical_FS!K22 -> 5488 | I49: =Historical_FS!L28+Historical_FS!L22 -> 7981
B50: Total Assets | C50: =C44 -> 13544 | D50: =D44 -> 16444 | E50: =E44 -> 21188 | F50: =F44 -> 27020 | G50: =G44 -> 31547 | H50: =H44 -> 40645 | I50: =I44 -> 60561
B51: EBIT/ Total Assets (C) | C51: =C49/C50 -> 0.16745422 | D51: =D49/D50 -> 0.093043055 | E51: =E49/E50 -> 0.14734756 | F51: =F49/F50 -> 0.17568468 | G51: =G49/G50 -> 0.16616477 | H51: =H49/H50 -> 0.13502276 | I51: =I49/I50 -> 0.13178448
B53: 4. Market Cap/ Long Term Liability
C54: =C48 -> 43921 | D54: =D48 -> 44286 | E54: =E48 -> 44651 | F54: =F48 -> 45016 | G54: =G48 -> 45382 | H54: =H48 -> 45747 | I54: =I48 -> 46112
B55: Market Cap | C55: ='Data Sheet'!E90*'Data Sheet'!E93 -> 82893.886 | D55: ='Data Sheet'!F90*'Data Sheet'!F93 -> 138323.68 | E55: ='Data Sheet'!G90*'Data Sheet'!G93 -> 225159.4 | F55: ='Data Sheet'!H90*'Data Sheet'!H93 -> 223272.82 | G55: ='Data Sheet'!I90*'Data Sheet'!I93 -> 337523.8 | H55: ='Data Sheet'!J90*'Data Sheet'!J93 -> 271964.21 | I55: ='Data Sheet'!K90*'Data Sheet'!K93 -> 350805.29
B56: Long Term Liability | C56: ='Data Sheet'!E59 -> 3562 | D56: ='Data Sheet'!F59 -> 5638 | E56: ='Data Sheet'!G59 -> 7275 | F56: ='Data Sheet'!H59 -> 9367 | G56: ='Data Sheet'!I59 -> 15528 | H56: ='Data Sheet'!J59 -> 20777 | I56: ='Data Sheet'!K59 -> 30621
B57: Market Cap/ Long Term Liability (D) | C57: =C55/C56 -> 23.271725 | D57: =D55/D56 -> 24.534175 | E57: =E55/E56 -> 30.949745 | F57: =F55/F56 -> 23.836108 | G57: =G55/G56 -> 21.736463 | H57: =H55/H56 -> 13.089677 | I57: =I55/I56 -> 11.456363
B59: 5. Sales/ Total Assets
C60: =C36 -> 43921 | D60: =D36 -> 44286 | E60: =E36 -> 44651 | F60: =F36 -> 45016 | G60: =G36 -> 45382 | H60: =H36 -> 45747 | I60: =I36 -> 46112
B61: Sales | C61: ='Data Sheet'!E17 -> 21052 | D61: ='Data Sheet'!F17 -> 21644 | E61: ='Data Sheet'!G17 -> 28799 | F61: ='Data Sheet'!H17 -> 40575 | G61: ='Data Sheet'!I17 -> 51084 | H61: ='Data Sheet'!J17 -> 60456 | I61: ='Data Sheet'!K17 -> 87584
B62: Total Assets | C62: =C44 -> 13544 | D62: =D44 -> 16444 | E62: =E44 -> 21188 | F62: =F44 -> 27020 | G62: =G44 -> 31547 | H62: =H44 -> 40645 | I62: =I44 -> 60561
B63: Sales/ Total Assets (E) | C63: =C61/C62 -> 1.5543414 | D63: =D61/D62 -> 1.3162248 | E63: =E61/E62 -> 1.3592128 | F63: =F61/F62 -> 1.5016654 | G63: =G61/G62 -> 1.6192982 | H63: =H61/H62 -> 1.4874154 | I63: =I61/I62 -> 1.4462113
B65: Atlman Z Score
C66: =C42 -> 43921 | D66: =D42 -> 44286 | E66: =E42 -> 44651 | F66: =F42 -> 45016 | G66: =G42 -> 45382 | H66: =H42 -> 45747 | I66: =I42 -> 46112
B67: Final Score | C67: =(C39*1.2)+(C45*1.4)+(C51*3.3)+(C57*0.6)+(C63*1) -> 17.407719 | D67: =(D39*1.2)+(D45*1.4)+(D51*3.3)+(D57*0.6)+(D63*1) -> 17.540464 | E67: =(E39*1.2)+(E45*1.4)+(E51*3.3)+(E57*0.6)+(E63*1) -> 21.797485 | F67: =(F39*1.2)+(F45*1.4)+(F51*3.3)+(F57*0.6)+(F63*1) -> 17.683608 | G67: =(G39*1.2)+(G45*1.4)+(G51*3.3)+(G57*0.6)+(G63*1) -> 16.336397 | H67: =(H39*1.2)+(H45*1.4)+(H51*3.3)+(H57*0.6)+(H63*1) -> 10.959 | I67: =(I39*1.2)+(I45*1.4)+(I51*3.3)+(I57*0.6)+(I63*1) -> 9.8247813
B68: Financial Stability | C68: =IF(C67<1.8, "Distressed",IF(C67>3,"Strong","Grey Zone")) -> Strong | D68: =IF(D67<1.8, "Distressed",IF(D67>3,"Strong","Grey Zone")) -> Strong | E68: =IF(E67<1.8, "Distressed",IF(E67>3,"Strong","Grey Zone")) -> Strong | F68: =IF(F67<1.8, "Distressed",IF(F67>3,"Strong","Grey Zone")) -> Strong | G68: =IF(G67<1.8, "Distressed",IF(G67>3,"Strong","Grey Zone")) -> Strong | H68: =IF(H67<1.8, "Distressed",IF(H67>3,"Strong","Grey Zone")) -> Strong | I68: =IF(I67<1.8, "Distressed",IF(I67>3,"Strong","Grey Zone")) -> Strong
B70: Disclamer: this project is only for educational purpose

Sheet Financials>
B1: ="Ratio Analysis: " & 'Data Sheet'!B1 -> Ratio Analysis: TITAN COMPANY LTD
B2: Historical Financial Statements
B3: Particulars | C3: 42825 | D3: 43190 | E3: 43555 | F3: 43921 | G3: 44286 | H3: 44651 | I3: 45016 | J3: 45382 | K3: 45747 | L3: 46112 | M3: Trend | N3: Mean | O3: Median
B5: Sales Growth | C5: =IFERROR(Historical_FS!C8,0) -> - | D5: =IFERROR(Historical_FS!D8,0) -> 0.21559284 | E5: =IFERROR(Historical_FS!E8,0) -> 0.22697284 | F5: =IFERROR(Historical_FS!F8,0) -> 0.064387022 | G5: =IFERROR(Historical_FS!G8,0) -> 0.028120844 | H5: =IFERROR(Historical_FS!H8,0) -> 0.3305766 | I5: =IFERROR(Historical_FS!I8,0) -> 0.40890309 | J5: =IFERROR(Historical_FS!J8,0) -> 0.25900185 | ... L5: =IFERROR(Historical_FS!L8,0) -> 0.44872304 | N5: =AVERAGE(D5:L5) -> 0.24063785 | O5: =MEDIAN(D5:L5) -> 0.22697284
B6: EBITDA Growth | C6: - | D6: =IFERROR(Historical_FS!D19/Historical_FS!C19-1,0) -> 0.41266432 | E6: =IFERROR(Historical_FS!E19/Historical_FS!D19-1,0) -> 0.21262012 | F6: =IFERROR(Historical_FS!F19/Historical_FS!E19-1,0) -> 0.23533572 | G6: =IFERROR(Historical_FS!G19/Historical_FS!F19-1,0) -> -0.29963459 | H6: =IFERROR(Historical_FS!H19/Historical_FS!G19-1,0) -> 0.93855072 | I6: =IFERROR(Historical_FS!I19/Historical_FS!H19-1,0) -> 0.45992823 | J6: =IFERROR(Historical_FS!J19/Historical_FS!I19-1,0) -> 0.083981975 | K6: =IFERROR(Historical_FS!K19/Historical_FS!J19-1,0) -> 0.075963719 | L6: =IFERROR(Historical_FS!L19/Historical_FS!K19-1,0) -> 0.46768528 | N6: =AVERAGE(D6:L6) -> 0.28745505 | O6: =MEDIAN(D6:L6) -> 0.23533572
B7: EBT Growth | C7: - | D7: =IFERROR(Historical_FS!D28/Historical_FS!C28-1,0) -> 0.57182635 | E7: =IFERROR(Historical_FS!E28/Historical_FS!D28-1,0) -> 0.27919701 | F7: =IFERROR(Historical_FS!F28/Historical_FS!E28-1,0) -> 0.074153376 | G7: =IFERROR(Historical_FS!G28/Historical_FS!F28-1,0) -> -0.36869648 | H7: =IFERROR(Historical_FS!H28/Historical_FS!G28-1,0) -> 1.1883949 | I7: =IFERROR(Historical_FS!I28/Historical_FS!H28-1,0) -> 0.53133609 | J7: =IFERROR(Historical_FS!J28/Historical_FS!I28-1,0) -> 0.039577243 | K7: =IFERROR(Historical_FS!K28/Historical_FS!J28-1,0) -> -0.019035258 | L7: =IFERROR(Historical_FS!L28/Historical_FS!K28-1,0) -> 0.49966924 | N7: =AVERAGE(D7:L7) -> 0.31071361 | O7: =MEDIAN(D7:L7) -> 0.27919701
B8: Net Profit Growth | C8: - | D8: =IFERROR(Historical_FS!D34/Historical_FS!C34-1,0) -> 0.58029773 | E8: =IFERROR(Historical_FS!E34/Historical_FS!D34-1,0) -> 0.26022089 | F8: =IFERROR(Historical_FS!F34/Historical_FS!E34-1,0) -> 0.075144925 | G8: =IFERROR(Historical_FS!G34/Historical_FS!F34-1,0) -> -0.34762224 | H8: =IFERROR(Historical_FS!H34/Historical_FS!G34-1,0) -> 1.2566735 | I8: =IFERROR(Historical_FS!I34/Historical_FS!H34-1,0) -> 0.48953594 | J8: =IFERROR(Historical_FS!J34/Historical_FS!I34-1,0) -> 0.067806964 | K8: =IFERROR(Historical_FS!K34/Historical_FS!J34-1,0) -> -0.045480549 | L8: =IFERROR(Historical_FS!L34/Historical_FS!K34-1,0) -> 0.52022775 | N8: =AVERAGE(D8:L8) -> 0.31742277 | O8: =MEDIAN(D8:L8) -> 0.26022089
B9: Dividend Growth | C9: - | D9: =IFERROR(Historical_FS!D42/Historical_FS!C42-1,0) -> 0.44227353 | E9: =IFERROR(Historical_FS!E42/Historical_FS!D42-1,0) -> 0.33335336 | F9: =IFERROR(Historical_FS!F42/Historical_FS!E42-1,0) -> -0.19801757 | G9: =IFERROR(Historical_FS!G42/Historical_FS!F42-1,0) -> 0 | H9: =IFERROR(Historical_FS!H42/Historical_FS!G42-1,0) -> 0.875 | I9: =IFERROR(Historical_FS!I42/Historical_FS!H42-1,0) -> 0.33333333 | J9: =IFERROR(Historical_FS!J42/Historical_FS!I42-1,0) -> 0.1 | K9: =IFERROR(Historical_FS!K42/Historical_FS!J42-1,0) -> 0 | L9: =IFERROR(Historical_FS!L42/Historical_FS!K42-1,0) -> 0.36363636 | N9: =AVERAGE(D9:L9) -> 0.24995322 | O9: =MEDIAN(D9:L9) -> 0.33333333
B11: Gross Margin | C11: =IFERROR(Historical_FS!C14,0) -> 0.26764086 | D11: =IFERROR(Historical_FS!D14,0) -> 0.26448268 | E11: =IFERROR(Historical_FS!E14,0) -> 0.26000328 | F11: =IFERROR(Historical_FS!F14,0) -> 0.26743302 | G11: =IFERROR(Historical_FS!G14,0) -> 0.23341342 | H11: =IFERROR(Historical_FS!H14,0) -> 0.24063336 | I11: =IFERROR(Historical_FS!I14,0) -> 0.24487985 | J11: =IFERROR(Historical_FS!J14,0) -> 0.22110641 | ... L11: =IFERROR(Historical_FS!L14,0) -> 0.19198712 | N11: =AVERAGE(C11:L11) -> 0.23999299 | O11: =MEDIAN(C11:L11) -> 0.2427566
B12: EBITDA Margin | C12: =IFERROR(Historical_FS!C20,0) -> 0.08776977 | D12: =IFERROR(Historical_FS!D20,0) -> 0.10199897 | E12: =IFERROR(Historical_FS!E20,0) -> 0.10080582 | F12: =IFERROR(Historical_FS!F20,0) -> 0.11699601 | G12: =IFERROR(Historical_FS!G20,0) -> 0.079698762 | H12: =IFERROR(Historical_FS!H20,0) -> 0.11611514 | I12: =IFERROR(Historical_FS!I20,0) -> 0.12032039 | J12: =IFERROR(Historical_FS!J20,0) -> 0.10359408 | ... L12: =IFERROR(Historical_FS!L20,0) -> 0.095416971 | N12: =AVERAGE(C12:L12) -> 0.10169001 | O12: =MEDIAN(C12:L12) -> 0.1014024
B13: EBIT Margin | C13: =IFERROR((Historical_FS!C19-Historical_FS!C25)/Historical_FS!C7,0) -> 0.079434696 | D13: =IFERROR((Historical_FS!D19-Historical_FS!D25)/Historical_FS!D7,0) -> 0.093845632 | E13: =IFERROR((Historical_FS!E19-Historical_FS!E25)/Historical_FS!E7,0) -> 0.09257265 | F13: =IFERROR((Historical_FS!F19-Historical_FS!F25)/Historical_FS!F7,0) -> 0.10046551 | G13: =IFERROR((Historical_FS!G19-Historical_FS!G25)/Historical_FS!G7,0) -> 0.062372944 | H13: =IFERROR((Historical_FS!H19-Historical_FS!H25)/Historical_FS!H7,0) -> 0.1022605 | I13: =IFERROR((Historical_FS!I19-Historical_FS!I25)/Historical_FS!I7,0) -> 0.10945163 | J13: =IFERROR((Historical_FS!J19-Historical_FS!J25)/Historical_FS!J7,0) -> 0.092161929 | ... L13: =IFERROR((Historical_FS!L19-Historical_FS!L25)/Historical_FS!L7,0) -> 0.085986025 | N13: =AVERAGE(C13:L13) -> 0.090127284 | O13: =MEDIAN(C13:L13) -> 0.092367289
B14: EBT Margin | C14: =IFERROR(Historical_FS!C29,0) -> 0.073392842 | D14: =IFERROR(Historical_FS!D29,0) -> 0.094900858 | E14: =IFERROR(Historical_FS!E29,0) -> 0.098940163 | F14: =IFERROR(Historical_FS!F29,0) -> 0.099847995 | G14: =IFERROR(Historical_FS!G29,0) -> 0.061310294 | H14: =IFERROR(Historical_FS!H29,0) -> 0.10083683 | I14: =IFERROR(Historical_FS!I29,0) -> 0.10959951 | J14: =IFERROR(Historical_FS!J29,0) -> 0.090498003 | ... L14: =IFERROR(Historical_FS!L29,0) -> 0.077651169 | N14: =AVERAGE(C14:L14) -> 0.08819909 | O14: =MEDIAN(C14:L14) -> 0.092699431
B15: Net Profit Margin | C15: =IFERROR(Historical_FS!C35,0) -> 0.052581927 | D15: =IFERROR(Historical_FS!D35,0) -> 0.068357675 | E15: =IFERROR(Historical_FS!E35,0) -> 0.070210006 | F15: =IFERROR(Historical_FS!F35,0) -> 0.070919628 | G15: =IFERROR(Historical_FS!G35,0) -> 0.045000924 | H15: =IFERROR(Historical_FS!H35,0) -> 0.076322095 | I15: =IFERROR(Historical_FS!I35,0) -> 0.08069008 | J15: =IFERROR(Historical_FS!J35,0) -> 0.068436301 | ... L15: =IFERROR(Historical_FS!L35,0) -> 0.057921538 | N15: =AVERAGE(C15:L15) -> 0.064563734 | O15: =MEDIAN(C15:L15) -> 0.068396988
B17: SalesExpenses%Sales | C17: =IFERROR(Historical_FS!C17,0) -> 0.17987109 | D17: =IFERROR(Historical_FS!D17,0) -> 0.16248371 | E17: =IFERROR(Historical_FS!E17,0) -> 0.15919745 | F17: =IFERROR(Historical_FS!F17,0) -> 0.15043701 | G17: =IFERROR(Historical_FS!G17,0) -> 0.15371466 | H17: =IFERROR(Historical_FS!H17,0) -> 0.12451821 | I17: =IFERROR(Historical_FS!I17,0) -> 0.12455946 | J17: =IFERROR(Historical_FS!J17,0) -> 0.11751233 | ... L17: =IFERROR(Historical_FS!L17,0) -> 0.09657015 | N17: =AVERAGE(C17:L17) -> 0.13830297 | O17: =MEDIAN(C17:L17) -> 0.13749824
B18: Depreciation%Sales | C18: =IFERROR(Historical_FS!C25/Historical_FS!C7,0) -> 0.008335074 | D18: =IFERROR(Historical_FS!D25/Historical_FS!D7,0) -> 0.0081533421 | E18: =IFERROR(Historical_FS!E25/Historical_FS!E7,0) -> 0.0082331742 | F18: =IFERROR(Historical_FS!F25/Historical_FS!F7,0) -> 0.016530496 | G18: =IFERROR(Historical_FS!G25/Historical_FS!G7,0) -> 0.017325818 | H18: =IFERROR(Historical_FS!H25/Historical_FS!H7,0) -> 0.013854648 | I18: =IFERROR(Historical_FS!I25/Historical_FS!I7,0) -> 0.010868762 | J18: =IFERROR(Historical_FS!J25/Historical_FS!J7,0) -> 0.011432151 | ... L18: =IFERROR(Historical_FS!L25/Historical_FS!L7,0) -> 0.0094309463 | N18: =AVERAGE(C18:L18) -> 0.011562729 | O18: =MEDIAN(C18:L18) -> 0.011150456
B19: OperatingIncome%Sales | C19: =C13 -> 0.079434696 | D19: =D13 -> 0.093845632 | E19: =E13 -> 0.09257265 | F19: =F13 -> 0.10046551 | G19: =G13 -> 0.062372944 | H19: =H13 -> 0.1022605 | I19: =I13 -> 0.10945163 | J19: =J13 -> 0.092161929 | ... L19: =L13 -> 0.085986025 | N19: =AVERAGE(C19:L19) -> 0.090127284 | O19: =MEDIAN(C19:L19) -> 0.092367289
B21: Return on Capital Employed | C21: =IFERROR((Historical_FS!C19-Historical_FS!C26)/(Historical_FS!C49+Historical_FS!C50+Historical_FS!C51),0) -> 0.19033979 | D21: =IFERROR((Historical_FS!D19-Historical_FS!D26)/(Historical_FS!D49+Historical_FS!D50+Historical_FS!D51),0) -> 0.24247434 | E21: =IFERROR((Historical_FS!E19-Historical_FS!E26)/(Historical_FS!E49+Historical_FS!E50+Historical_FS!E51),0) -> 0.23558444 | F21: =IFERROR((Historical_FS!F19-Historical_FS!F26)/(Historical_FS!F49+Historical_FS!F50+Historical_FS!F51),0) -> 0.24073731 | G21: =IFERROR((Historical_FS!G19-Historical_FS!G26)/(Historical_FS!G49+Historical_FS!G50+Historical_FS!G51),0) -> 0.13132719 | H21: =IFERROR((Historical_FS!H19-Historical_FS!H26)/(Historical_FS!H49+Historical_FS!H50+Historical_FS!H51),0) -> 0.20171228 | I21: =IFERROR((Historical_FS!I19-Historical_FS!I26)/(Historical_FS!I49+Historical_FS!I50+Historical_FS!I51),0) -> 0.23008715 | J21: =IFERROR((Historical_FS!J19-Historical_FS!J26)/(Historical_FS!J49+Historical_FS!J50+Historical_FS!J51),0) -> 0.21235057 | ... L21: =IFERROR((Historical_FS!L19-Historical_FS!L26)/(Historical_FS!L49+Historical_FS!L50+Historical_FS!L51),0) -> 0.18040304 | N21: =AVERAGE(C21:L21) -> 0.20407511 | O21: =MEDIAN(C21:L21) -> 0.20703142
B22: Retained Earnings% | C22: =Historical_FS!C45 -> 0.66895652 | D22: =Historical_FS!D45 -> 0.69787006 | E22: =Historical_FS!E45 -> 0.68033702 | F22: =Historical_FS!F45 -> 0.76155392 | G22: =Historical_FS!G45 -> 0.63449692 | H22: =Historical_FS!H45 -> 0.69631483 | I22: =Historical_FS!I45 -> 0.72816127 | J22: =Historical_FS!J45 -> 0.71996568 | ... L22: =Historical_FS!L45 -> 0.73684211 | N22: =AVERAGE(C22:L22) -> 0.7031121 | O22: =MEDIAN(C22:L22) -> 0.70224639
B23: Return on Equity | C23: =IFERROR(Historical_FS!C34/SUM(Historical_FS!C49:C50),0) -> 0.16474891 | D23: =IFERROR(Historical_FS!D34/SUM(Historical_FS!D49:D50),0) -> 0.21649037 | E23: =IFERROR(Historical_FS!E34/SUM(Historical_FS!E49:E50),0) -> 0.228767 | F23: =IFERROR(Historical_FS!F34/SUM(Historical_FS!F49:F50),0) -> 0.22387164 | G23: =IFERROR(Historical_FS!G34/SUM(Historical_FS!G49:G50),0) -> 0.12991863 | H23: =IFERROR(Historical_FS!H34/SUM(Historical_FS!H49:H50),0) -> 0.23626787 | I23: =IFERROR(Historical_FS!I34/SUM(Historical_FS!I49:I50),0) -> 0.27626361 | J23: =IFERROR(Historical_FS!J34/SUM(Historical_FS!J49:J50),0) -> 0.37219206 | ... L23: =IFERROR(Historical_FS!L34/SUM(Historical_FS!L49:L50),0) -> 0.32305929 | N23: =AVERAGE(C23:L23) -> 0.24586578 | O23: =MEDIAN(C23:L23) -> 0.23251743
B24: Self Sustained Growth Rate | C24: =IFERROR(C22*C23,0) -> 0.11020986 | D24: =IFERROR(D22*D23,0) -> 0.15108215 | E24: =IFERROR(E22*E23,0) -> 0.15563866 | F24: =IFERROR(F22*F23,0) -> 0.17049033 | G24: =IFERROR(G22*G23,0) -> 0.082432973 | H24: =IFERROR(H22*H23,0) -> 0.16451682 | I24: =IFERROR(I22*I23,0) -> 0.20116446 | J24: =IFERROR(J22*J23,0) -> 0.26796551 | ... L24: =IFERROR(L22*L23,0) -> 0.23804369 | N24: =AVERAGE(C24:L24) -> 0.17444006 | O24: =MEDIAN(C24:L24) -> 0.16750358
B25: Interest Coverage Ratio | C25: =IFERROR((Historical_FS!C19-Historical_FS!C25)/Historical_FS!C22,0) -> 27.911235 | D25: =IFERROR((Historical_FS!D19-Historical_FS!D25)/Historical_FS!D22,0) -> 28.585979 | E25: =IFERROR((Historical_FS!E19-Historical_FS!E25)/Historical_FS!E22,0) -> 34.848687 | F25: =IFERROR((Historical_FS!F19-Historical_FS!F25)/Historical_FS!F22,0) -> 12.740964 | G25: =IFERROR((Historical_FS!G19-Historical_FS!G25)/Historical_FS!G22,0) -> 6.6502463 | H25: =IFERROR((Historical_FS!H19-Historical_FS!H25)/Historical_FS!H22,0) -> 13.509174 | I25: =IFERROR((Historical_FS!I19-Historical_FS!I25)/Historical_FS!I22,0) -> 14.803333 | J25: =IFERROR((Historical_FS!J19-Historical_FS!J25)/Historical_FS!J22,0) -> 7.6058158 | ... L25: =IFERROR((Historical_FS!L19-Historical_FS!L25)/Historical_FS!L22,0) -> 6.3822034 | N25: =AVERAGE(C25:L25) -> 15.828528 | O25: =MEDIAN(C25:L25) -> 13.125069
B27: Debtor Turnover Ratio | C27: =IFERROR(Historical_FS!C7/Historical_FS!C61,0) -> 63.87683 | D27: =IFERROR(Historical_FS!D7/Historical_FS!D61,0) -> 54.515777 | E27: =IFERROR(Historical_FS!E7/Historical_FS!E61,0) -> 47.041313 | F27: =IFERROR(Historical_FS!F7/Historical_FS!F61,0) -> 67.474359 | G27: =IFERROR(Historical_FS!G7/Historical_FS!G61,0) -> 59.136612 | H27: =IFERROR(Historical_FS!H7/Historical_FS!H61,0) -> 50.971681 | I27: =IFERROR(Historical_FS!I7/Historical_FS!I61,0) -> 60.200297 | J27: =IFERROR(Historical_FS!J7/Historical_FS!J61,0) -> 50.180747 | ... L27: =IFERROR(Historical_FS!L7/Historical_FS!L61,0) -> 95.615721 | N27: =AVERAGE(C27:L27) -> 60.562008 | O27: =MEDIAN(C27:L27) -> 57.871677
B28: Creditor Turnover Ratio | C28: =IFERROR(Historical_FS!C7/Historical_FS!C52,0) -> 5.7837846 | D28: =IFERROR(Historical_FS!D7/Historical_FS!D52,0) -> 5.8828057 | E28: =IFERROR(Historical_FS!E7/Historical_FS!E52,0) -> 6.0918653 | F28: =IFERROR(Historical_FS!F7/Historical_FS!F52,0) -> 6.3543616 | G28: =IFERROR(Historical_FS!G7/Historical_FS!G52,0) -> 6.5409489 | H28: =IFERROR(Historical_FS!H7/Historical_FS!H52,0) -> 6.2470716 | I28: =IFERROR(Historical_FS!I7/Historical_FS!I52,0) -> 6.9932782 | J28: =IFERROR(Historical_FS!J7/Historical_FS!J52,0) -> 7.7096287 | ... L28: =IFERROR(Historical_FS!L7/Historical_FS!L52,0) -> 6.1518578 | N28: =AVERAGE(C28:L28) -> 6.5088936 | O28: =MEDIAN(C28:L28) -> 6.3007166
B29: Inventory Turnover | C29: =IFERROR(Historical_FS!C7/Historical_FS!C62,0) -> 2.6921498 | D29: =IFERROR(Historical_FS!D7/Historical_FS!D62,0) -> 2.7207098 | E29: =IFERROR(Historical_FS!E7/Historical_FS!E62,0) -> 2.8099198 | F29: =IFERROR(Historical_FS!F7/Historical_FS!F62,0) -> 2.5980501 | G29: =IFERROR(Historical_FS!G7/Historical_FS!G62,0) -> 2.574215 | H29: =IFERROR(Historical_FS!H7/Historical_FS!H62,0) -> 2.1161731 | I29: =IFERROR(Historical_FS!I7/Historical_FS!I62,0) -> 2.4466353 | J29: =IFERROR(Historical_FS!J7/Historical_FS!J62,0) -> 2.681434 | ... L29: =IFERROR(Historical_FS!L7/Historical_FS!L62,0) -> 2.0490841 | N29: =AVERAGE(C29:L29) -> 2.4833418 | O29: =MEDIAN(C29:L29) -> 2.5861326
B30: Fixed Asset Turnover | C30: =IFERROR(Historical_FS!C7/Historical_FS!C55,0) -> 11.155554 | D30: =IFERROR(Historical_FS!D7/Historical_FS!D55,0) -> 10.937482 | E30: =IFERROR(Historical_FS!E7/Historical_FS!E55,0) -> 12.624883 | F30: =IFERROR(Historical_FS!F7/Historical_FS!F55,0) -> 7.9954425 | G30: =IFERROR(Historical_FS!G7/Historical_FS!G55,0) -> 8.5786762 | H30: =IFERROR(Historical_FS!H7/Historical_FS!H55,0) -> 11.320362 | I30: =IFERROR(Historical_FS!I7/Historical_FS!I55,0) -> 13.534023 | J30: =IFERROR(Historical_FS!J7/Historical_FS!J55,0) -> 13.772985 | ... L30: =IFERROR(Historical_FS!L7/Historical_FS!L55,0) -> 12.733934 | N30: =AVERAGE(C30:L30) -> 11.753665 | O30: =MEDIAN(C30:L30) -> 11.972622
B31: Capital Turnover Ratio | C31: =IFERROR(Historical_FS!C7/SUM(Historical_FS!C49:C50),0) -> 3.1331851 | D31: =IFERROR(Historical_FS!D7/SUM(Historical_FS!D49:D50),0) -> 3.1670236 | E31: =IFERROR(Historical_FS!E7/SUM(Historical_FS!E49:E50),0) -> 3.2583248 | F31: =IFERROR(Historical_FS!F7/SUM(Historical_FS!F49:F50),0) -> 3.1566952 | G31: =IFERROR(Historical_FS!G7/SUM(Historical_FS!G49:G50),0) -> 2.8870215 | H31: =IFERROR(Historical_FS!H7/SUM(Historical_FS!H49:H50),0) -> 3.0956681 | I31: =IFERROR(Historical_FS!I7/SUM(Historical_FS!I49:I50),0) -> 3.4237617 | J31: =IFERROR(Historical_FS!J7/SUM(Historical_FS!J49:J50),0) -> 5.438518 | ... L31: =IFERROR(Historical_FS!L7/SUM(Historical_FS!L49:L50),0) -> 5.577533 | N31: =AVERAGE(C31:L31) -> 3.8338694 | O31: =MEDIAN(C31:L31) -> 3.2126742
B33: (In Days)
B34: Debtor Days | C34: =IFERROR(365/C27,0) -> 5.714122 | D34: =IFERROR(365/D27,0) -> 6.6953095 | E34: =IFERROR(365/E27,0) -> 7.7591372 | F34: =IFERROR(365/F27,0) -> 5.4094623 | G34: =IFERROR(365/G27,0) -> 6.1721493 | H34: =IFERROR(365/H27,0) -> 7.1608389 | I34: =IFERROR(365/I27,0) -> 6.063093 | J34: =IFERROR(365/J27,0) -> 7.2737061 | ... L34: =IFERROR(365/L27,0) -> 3.8173639 | N34: =AVERAGE(C34:L34) -> 6.2513177 | O34: =MEDIAN(C34:L34) -> 6.3100723
B35: Payable Days | C35: =IFERROR(365/C28,0) -> 63.107468 | D35: =IFERROR(365/D28,0) -> 62.045225 | E35: =IFERROR(365/E28,0) -> 59.915967 | F35: =IFERROR(365/F28,0) -> 57.440861 | G35: =IFERROR(365/G28,0) -> 55.802301 | H35: =IFERROR(365/H28,0) -> 58.427376 | I35: =IFERROR(365/I28,0) -> 52.192976 | J35: =IFERROR(365/J28,0) -> 47.343395 | ... L35: =IFERROR(365/L28,0) -> 59.33167 | N35: =AVERAGE(C35:L35) -> 56.537997 | O35: =MEDIAN(C35:L35) -> 57.934118
B36: Inventory Days | C36: =IFERROR(365/C29,0) -> 135.57938 | D36: =IFERROR(365/D29,0) -> 134.15617 | E36: =IFERROR(365/E29,0) -> 129.89694 | F36: =IFERROR(365/F29,0) -> 140.48998 | G36: =IFERROR(365/G29,0) -> 141.7908 | H36: =IFERROR(365/H29,0) -> 172.48116 | I36: =IFERROR(365/I29,0) -> 149.18447 | J36: =IFERROR(365/J29,0) -> 136.12119 | ... L36: =IFERROR(365/L29,0) -> 178.12837 | N36: =AVERAGE(C36:L36) -> 148.79879 | O36: =MEDIAN(C36:L36) -> 141.14039
B37: Cash Conversion Cycle | C37: =SUM(C34,C36)-C35 -> 78.186034 | D37: =SUM(D34,D36)-D35 -> 78.806255 | E37: =SUM(E34,E36)-E35 -> 77.740114 | F37: =SUM(F34,F36)-F35 -> 88.458579 | G37: =SUM(G34,G36)-G35 -> 92.160645 | H37: =SUM(H34,H36)-H35 -> 121.21463 | I37: =SUM(I34,I36)-I35 -> 103.05459 | J37: =SUM(J34,J36)-J35 -> 96.051503 | ... L37: =SUM(L34,L36)-L35 -> 122.61406 | N37: =AVERAGE(C37:L37) -> 98.512113 | O37: =MEDIAN(C37:L37) -> 94.106074
B39: CFO/Sales | C39: =IFERROR(Historical_FS!C82/Historical_FS!C7,0) -> 0.19817764 | D39: =IFERROR(Historical_FS!D82/Historical_FS!D7,0) -> -0.079839849 | E39: =IFERROR(Historical_FS!E82/Historical_FS!E7,0) -> 0.047475746 | F39: =IFERROR(Historical_FS!F82/Historical_FS!F7,0) -> -0.12445373 | G39: =IFERROR(Historical_FS!G82/Historical_FS!G7,0) -> 0.31232674 | H39: =IFERROR(Historical_FS!H82/Historical_FS!H7,0) -> -0.1369492 | I39: =IFERROR(Historical_FS!I82/Historical_FS!I7,0) -> -0.025705484 | J39: =IFERROR(Historical_FS!J82/Historical_FS!J7,0) -> -0.01646308 | ... L39: =IFERROR(Historical_FS!L82/Historical_FS!L7,0) -> 0.051036719 | N39: =AVERAGE(C39:L39) -> 0.013021381 | O39: =MEDIAN(C39:L39) -> -0.021084282
B40: CFO/Total Assets | C40: =IFERROR(Historical_FS!C82/Historical_FS!C66,0) -> 0.31257545 | D40: =IFERROR(Historical_FS!D82/Historical_FS!D66,0) -> -0.13517431 | E40: =IFERROR(Historical_FS!E82/Historical_FS!E66,0) -> 0.080188969 | F40: =IFERROR(Historical_FS!F82/Historical_FS!F66,0) -> -0.19344359 | G40: =IFERROR(Historical_FS!G82/Historical_FS!G66,0) -> 0.41109219 | H40: =IFERROR(Historical_FS!H82/Historical_FS!H66,0) -> -0.1861431 | I40: =IFERROR(Historical_FS!I82/Historical_FS!I66,0) -> -0.038601036 | J40: =IFERROR(Historical_FS!J82/Historical_FS!J66,0) -> -0.026658636 | ... L40: =IFERROR(Historical_FS!L82/Historical_FS!L66,0) -> 0.073809878 | N40: =AVERAGE(C40:L40) -> 0.015575875 | O40: =MEDIAN(C40:L40) -> -0.032629836
B41: CFO/Total Debt | C41: =IFERROR(Historical_FS!C82/Historical_FS!C51,0) -> 1.3960678 | D41: =IFERROR(Historical_FS!D82/Historical_FS!D51,0) -> -0.76108361 | E41: =IFERROR(Historical_FS!E82/Historical_FS!E51,0) -> 0.39239776 | F41: =IFERROR(Historical_FS!F82/Historical_FS!F51,0) -> -0.73554183 | G41: =IFERROR(Historical_FS!G82/Historical_FS!G51,0) -> 1.1990067 | H41: =IFERROR(Historical_FS!H82/Historical_FS!H51,0) -> -0.54213058 | I41: =IFERROR(Historical_FS!I82/Historical_FS!I51,0) -> -0.11134835 | J41: =IFERROR(Historical_FS!J82/Historical_FS!J51,0) -> -0.054160227 | ... L41: =IFERROR(Historical_FS!L82/Historical_FS!L51,0) -> 0.14597825 | N41: =AVERAGE(C41:L41) -> 0.065161946 | O41: =MEDIAN(C41:L41) -> -0.082754289

Sheet Data Sheet
A1: COMPANY NAME | B1: TITAN COMPANY LTD | E1: =IF(B2<>B3, "A NEW VERSION OF THE WORKSHEET IS AVAILABLE", "")
A2: LATEST VERSION | B2: 2.1 | E2: PLEASE DO NOT MAKE ANY CHANGES TO THIS SHEET
A3: CURRENT VERSION | B3: 2.1
A5: META
A6: Number of shares | B6: =IF(B9>0, B9/B8, 0) -> 88.778617
A7: Face Value | B7: 1
A8: Current Price | B8: 4515.7
A9: Market Capitalization | B9: 400897.6
A15: PROFIT & LOSS
A16: Report Date | B16: 42825 | C16: 43190 | D16: 43555 | E16: 43921 | F16: 44286 | G16: 44651 | H16: 45016 | I16: 45382 | J16: 45747 | K16: 46112
A17: Sales | B17: 13260.83 | C17: 16119.77 | D17: 19778.52 | E17: 21052 | F17: 21644 | G17: 28799 | H17: 40575 | I17: 51084 | J17: 60456 | K17: 87584
A18: Raw Material Cost | B18: 9821.14 | C18: 12664.83 | D18: 15170.66 | E18: 16033 | F18: 16292 | G18: 26436 | H18: 32589 | I18: 42103 | J18: 55271 | K18: 80243
A19: Change in Inventory | B19: 313.71 | C19: 978.61 | D19: 776.41 | E19: 878 | F19: -122 | G19: 4795 | H19: 2234 | I19: 2671 | J19: 7815 | K19: 9936
A20: Power and Fuel | B20: 43.84 | C20: 45.32 | D20: 48.51 | E20: 52 | F20: 37 | G20: 45 | H20: 59 | I20: 71 | J20: 78 | K20: 87
A21: Other Mfr. Exp | B21: 160.42 | C21: 124.83 | D21: 193.28 | E21: 215 | F21: 141 | G21: 183 | H21: 225 | I21: 286 | J21: 326 | K21: 375
A22: Employee Cost | B22: 894.32 | C22: 906.26 | D22: 1024.44 | E22: 1204 | F22: 1069 | G22: 1356 | H22: 1656 | I22: 1875 | J22: 2164 | K22: 2692
A23: Selling and admin | B23: 1211.16 | C23: 1277.81 | D23: 1454.32 | E23: 1470 | F23: 1029 | G23: 1697 | H23: 2715 | I23: 3249 | J23: 3494 | K23: 4185
A24: Other Expenses | B24: 279.76 | C24: 435.13 | D24: 669.93 | E24: 493 | F24: 1229 | G24: 533 | H24: 683 | I24: 879 | J24: 1244 | K24: 1581
A25: Other Income | B25: -42.38 | C25: 69.93 | D25: 178.48 | E25: 153 | F25: 180 | G25: 177 | H25: 306 | I25: 534 | J25: 487 | K25: 450
A26: Depreciation | B26: 110.53 | C26: 131.43 | D26: 162.84 | E26: 348 | F26: 375 | G26: 399 | H26: 441 | I26: 584 | J26: 693 | K26: 826
A27: Interest | B27: 37.74 | C27: 52.92 | D27: 52.54 | E27: 166 | F27: 203 | G27: 218 | H27: 300 | I27: 619 | J27: 953 | K27: 1180
... A31: Dividend Amount | B31: 230.83 | C31: 332.92 | D31: 443.9 | E31: 356 | F31: 356 | G31: 667.5 | H31: 890 | I31: 979 | J31: 979 | K31: 1335
A40: Quarters
A41: Report Date | B41: 45382 | C41: 45473 | D41: 45565 | E41: 45657 | F41: 45747 | G41: 45838 | H41: 45930 | I41: 46022 | J41: 46112 | K41: 46203
A42: Sales | B42: 12494 | C42: 13266 | D42: 14534 | E42: 17740 | F42: 14916 | G42: 16523 | H42: 18725 | I42: 25416 | J42: 26920 | K42: 21356
A43: Expenses | B43: 11303 | C43: 12019 | D43: 13298 | E43: 16066 | F43: 13379 | G43: 14693 | H43: 16850 | I43: 22703 | J43: 24982 | K43: 18466
A44: Other Income | B44: 159 | C44: 120 | D44: 123 | E44: 128 | F44: 116 | G44: 105 | H44: 113 | I44: -1 | J44: 235 | K44: 148
A45: Depreciation | B45: 158 | C45: 164 | D45: 171 | E45: 175 | F45: 183 | G45: 184 | H45: 189 | I45: 207 | J45: 246 | K45: 256
A46: Interest | B46: 201 | C46: 230 | D46: 240 | E46: 231 | F46: 252 | G46: 271 | H46: 277 | I46: 282 | J46: 350 | K46: 353
A47: Profit before tax | B47: 991 | C47: 973 | D47: 948 | E47: 1396 | F47: 1218 | G47: 1480 | H47: 1522 | I47: 2223 | J47: 1577 | K47: 2429
A48: Tax | B48: 220 | C48: 258 | D48: 244 | E48: 349 | F48: 347 | G48: 389 | H48: 402 | I48: 539 | J48: 398 | K48: 652
A49: Net profit | B49: 771 | C49: 715 | D49: 704 | E49: 1047 | F49: 871 | G49: 1091 | H49: 1120 | I49: 1684 | J49: 1179 | K49: 1777
A50: Operating Profit | B50: 1191 | C50: 1247 | D50: 1236 | E50: 1674 | F50: 1537 | G50: 1830 | H50: 1875 | I50: 2713 | J50: 1938 | K50: 2890
A55: BALANCE SHEET
A56: Report Date | B56: 42825 | C56: 43190 | D56: 43555 | E56: 43921 | F56: 44286 | G56: 44651 | H56: 45016 | I56: 45382 | J56: 45747 | K56: 46112
A57: Equity Share Capital | B57: 88.78 | C57: 88.78 | D57: 88.78 | E57: 89 | F57: 89 | G57: 89 | H57: 89 | I57: 89 | J57: 89 | K57: 89
A58: Reserves | B58: 4143.6 | C58: 5001.1 | D58: 5981.37 | E58: 6580 | F58: 7408 | G58: 9214 | H58: 11762 | I58: 9304 | J58: 11535 | K58: 15614
A59: Borrowings | B59: 1882.43 | C59: 1691.01 | D59: 2392.98 | E59: 3562 | F59: 5638 | G59: 7275 | H59: 9367 | I59: 15528 | J59: 20777 | K59: 30621
A60: Other Liabilities | B60: 2292.76 | C60: 2740.15 | D60: 3246.71 | E60: 3313 | F60: 3309 | G60: 4610 | H60: 5802 | I60: 6626 | J60: 8244 | K60: 14237
A61: Total | B61: 8407.57 | C61: 9521.04 | D61: 11709.84 | E61: 13544 | F61: 16444 | G61: 21188 | H61: 27020 | I61: 31547 | J61: 40645 | K61: 60561
A62: Net Block | B62: 1188.72 | C62: 1473.81 | D62: 1566.63 | E62: 2633 | F62: 2523 | G62: 2544 | H62: 2998 | I62: 3709 | J62: 4062 | K62: 6878
A63: Capital Work in Progress | B63: 152.07 | C63: 43.37 | D63: 31.77 | E63: 18 | F63: 32 | G63: 85 | H63: 144 | I63: 97 | J63: 105 | K63: 163
A64: Investments | B64: 430.73 | C64: 35.99 | D64: 108.42 | E64: 158 | F64: 2824 | G64: 294 | H64: 2515 | I64: 2345 | J64: 1988 | K64: 3506
A65: Other Assets | B65: 6636.05 | C65: 7967.87 | D65: 10003.02 | E65: 10735 | F65: 11065 | G65: 18265 | H65: 21363 | I65: 25396 | J65: 34490 | K65: 50014
A66: Total | B66: 8407.57 | C66: 9521.04 | D66: 11709.84 | E66: 13544 | F66: 16444 | G66: 21188 | H66: 27020 | I66: 31547 | J66: 40645 | K66: 60561
A67: Receivables | B67: 207.6 | C67: 295.69 | D67: 420.45 | E67: 312 | F67: 366 | G67: 565 | H67: 674 | I67: 1018 | J67: 1068 | K67: 916
... A70: No. of Equity Shares | B70: 887786160 | C70: 887786160 | D70: 887786160 | E70: 887786160 | F70: 887786160 | G70: 887786160 | H70: 890000000 | I70: 890000000 | J70: 890000000 | K70: 890000000
A71: New Bonus Shares
A72: Face value | B72: 1 | C72: 1 | D72: 1 | E72: 1 | F72: 1 | G72: 1 | H72: 1 | I72: 1 | J72: 1 | K72: 1
A80: CASH FLOW:
A81: Report Date | B81: 42825 | C81: 43190 | D81: 43555 | E81: 43921 | F81: 44286 | G81: 44651 | H81: 45016 | I81: 45382 | J81: 45747 | K81: 46112
A82: Cash from Operating Activity | B82: 1712.3 | C82: -51.12 | D82: 1242.92 | E82: -348 | F82: 4139 | G82: -724 | H82: 1370 | I82: 1695 | J82: -541 | K82: 5590
A83: Cash from Investing Activity | B83: -953.15 | C83: 97.62 | D83: -796.61 | E83: 235 | F83: -2799 | G83: 1165 | H83: -1814 | I83: -189 | J83: 546 | K83: -2965
A84: Cash from Financing Activity | B84: -165.6 | C84: -252.45 | D84: -488.83 | E84: -242 | F84: -1234 | G84: -403 | H84: 457 | I84: -1329 | J84: -7 | K84: -2159
A85: Net Cash Flow | B85: 593.55 | C85: -205.95 | D85: -42.52 | E85: -355 | F85: 106 | G85: 38 | H85: 13 | I85: 177 | J85: -2 | K85: 466
A90: PRICE: | B90: 462.75 | C90: 942.3 | D90: 1141.85 | E90: 933.7 | F90: 1558.05 | G90: 2536.15 | H90: 2514.9 | I90: 3801.8 | J90: 3063.35 | K90: 3951.4
A92: DERIVED:
A93: Adjusted Equity Shares in Cr | B93: 88.78 | C93: 88.78 | D93: 88.78 | E93: 88.78 | F93: 88.78 | G93: 88.78 | H93: 88.78 | I93: 88.78 | J93: 88.78 | K93: 88.78

Sheet Forecasting
B2: ="Forecasting:" & 'Data Sheet'!B1 -> Forecasting:TITAN COMPANY LTD
B4: Forecasting: Sales | G4: Forecasting: EBITDA | L4: Forecasting: EPS
B5: Year Weight | C5: Year | D5: Sales | E5: Sales Growth | G5: Year Weight | H5: Year | I5: EBITDA | J5: EBIDTA Growth | L5: Year Weight | M5: Year | N5: EPS | O5: EPS Growth
B6: 1 | C6: ='Data Sheet'!B16 -> 42825 | D6: {=TRANSPOSE('Data Sheet'!B17:K17)} -> 13260.83 | E6: - | G6: 1 | H6: ='Data Sheet'!B16 -> 42825 | I6: {=TRANSPOSE(Historical_FS!C19:L19)} -> 1163.9 | J6: - | L6: 1 | M6: ='Data Sheet'!B16 -> 42825 | N6: {=TRANSPOSE(Historical_FS!C39:L39)} -> 7.8540212 | O6: -
B7: 2 | C7: =C6+365 -> 43190 | D7: 16119.77 | E7: =D7/D6-1 -> 0.21559284 | G7: 2 | H7: =H6+365 -> 43190 | I7: 1644.2 | J7: =I7/I6-1 -> 0.41266432 | L7: 2 | M7: =M6+365 -> 43190 | N7: 12.411692 | O7: =N7/N6-1 -> 0.58029773
B8: 3 | C8: =C7+365 -> 43555 | D8: 19778.52 | E8: =D8/D7-1 -> 0.22697284 | G8: 3 | H8: =H7+365 -> 43555 | I8: 1993.79 | J8: =I8/I7-1 -> 0.21262012 | L8: 3 | M8: =M7+365 -> 43555 | N8: 15.641473 | O8: =N8/N7-1 -> 0.26022089
B9: 4 | C9: =C8+365 -> 43920 | D9: 21052 | E9: =D9/D8-1 -> 0.064387022 | G9: 4 | H9: =H8+365 -> 43920 | I9: 2463 | J9: =I9/I8-1 -> 0.23533572 | L9: 4 | M9: =M8+365 -> 43920 | N9: 16.816851 | O9: =N9/N8-1 -> 0.075144925
B10: 5 | C10: =C9+365 -> 44285 | D10: 21644 | E10: =D10/D9-1 -> 0.028120844 | G10: 5 | H10: =H9+365 -> 44285 | I10: 1725 | J10: =I10/I9-1 -> -0.29963459 | L10: 5 | M10: =M9+365 -> 44285 | N10: 10.970939 | O10: =N10/N9-1 -> -0.34762224
B11: 6 | C11: =C10+365 -> 44650 | D11: 28799 | E11: =D11/D10-1 -> 0.3305766 | G11: 6 | H11: =H10+365 -> 44650 | I11: 3344 | J11: =I11/I10-1 -> 0.93855072 | L11: 6 | M11: =M10+365 -> 44650 | N11: 24.757828 | O11: =N11/N10-1 -> 1.2566735
B12: 7 | C12: =C11+365 -> 45015 | D12: 40575 | E12: =D12/D11-1 -> 0.40890309 | G12: 7 | H12: =H11+365 -> 45015 | I12: 4882 | J12: =I12/I11-1 -> 0.45992823 | L12: 7 | M12: =M11+365 -> 45015 | N12: 36.877675 | O12: =N12/N11-1 -> 0.48953594
B13: 8 | C13: =C12+365 -> 45380 | D13: 51084 | E13: =D13/D12-1 -> 0.25900185 | G13: 8 | H13: =H12+365 -> 45380 | I13: 5292 | J13: =I13/I12-1 -> 0.083981975 | L13: 8 | M13: =M12+365 -> 45380 | N13: 39.378238 | O13: =N13/N12-1 -> 0.067806964
B14: 9 | C14: =C13+365 -> 45745 | D14: 60456 | E14: =D14/D13-1 -> 0.18346253 | G14: 9 | H14: =H13+365 -> 45745 | I14: 5694 | J14: =I14/I13-1 -> 0.075963719 | L14: 9 | M14: =M13+365 -> 45745 | N14: 37.587294 | O14: =N14/N13-1 -> -0.045480549
B15: 10 | C15: =C14+365 -> 46110 | D15: 87584 | E15: =D15/D14-1 -> 0.44872304 | G15: 10 | H15: =H14+365 -> 46110 | I15: 8357 | J15: =I15/I14-1 -> 0.46768528 | L15: 10 | M15: =M14+365 -> 46110 | N15: 57.141248 | O15: =N15/N14-1 -> 0.52022775
B16: 11 | C16: =C15+365 -> 46475 | D16: =FORECAST(B16,$D$6:$D$15,$B$6:$B$15) -> 76085.763 | E16: =D16/D15-1 -> -0.13128239 | G16: 11 | H16: =H15+365 -> 46475 | I16: =FORECAST(G16,$I$6:$I$15,$G$6:$G$15) -> 7604.3407 | J16: =I16/I15-1 -> -0.09006334 | L16: 11 | M16: =M15+365 -> 46475 | N16: =FORECAST(L16,$N$6:$N$15,$L$6:$L$15) -> 53.025974 | O16: =N16/N15-1 -> -0.072019318
B17: 12 | C17: =C16+365 -> 46840 | D17: =FORECAST(B17,$D$6:$D$15,$B$6:$B$15) -> 83367.664 | E17: =D17/D16-1 -> 0.095706475 | G17: 12 | H17: =H16+365 -> 46840 | I17: =FORECAST(G17,$I$6:$I$15,$G$6:$G$15) -> 8322.241 | J17: =I17/I16-1 -> 0.094406647 | L17: 12 | M17: =M16+365 -> 46840 | N17: =FORECAST(L17,$N$6:$N$15,$L$6:$L$15) -> 57.950019 | O17: =N17/N16-1 -> 0.092861003
B18: 13 | C18: =C17+365 -> 47205 | D18: =FORECAST(B18,$D$6:$D$15,$B$6:$B$15) -> 90649.564 | E18: =D18/D17-1 -> 0.087346819 | G18: 13 | H18: =H17+365 -> 47205 | I18: =FORECAST(G18,$I$6:$I$15,$G$6:$G$15) -> 9040.1413 | J18: =I18/I17-1 -> 0.086262859 | L18: 13 | M18: =M17+365 -> 47205 | N18: =FORECAST(L18,$N$6:$N$15,$L$6:$L$15) -> 62.874065 | O18: =N18/N17-1 -> 0.084970552
B19: 14 | C19: =C18+365 -> 47570 | D19: =FORECAST(B19,$D$6:$D$15,$B$6:$B$15) -> 97931.464 | E19: =D19/D18-1 -> 0.080330229 | G19: 14 | H19: =H18+365 -> 47570 | I19: =FORECAST(G19,$I$6:$I$15,$G$6:$G$15) -> 9758.0416 | J19: =I19/I18-1 -> 0.079412509 | L19: 14 | M19: =M18+365 -> 47570 | N19: =FORECAST(L19,$N$6:$N$15,$L$6:$L$15) -> 67.79811 | O19: =N19/N18-1 -> 0.078315998
B20: 15 | C20: =C19+365 -> 47935 | D20: =FORECAST(B20,$D$6:$D$15,$B$6:$B$15) -> 105213.36 | E20: =D20/D19-1 -> 0.074357106 | G20: 15 | H20: =H19+365 -> 47935 | I20: =FORECAST(G20,$I$6:$I$15,$G$6:$G$15) -> 10475.942 | J20: =I20/I19-1 -> 0.073570121 | L20: 15 | M20: =M19+365 -> 47935 | N20: =FORECAST(L20,$N$6:$N$15,$L$6:$L$15) -> 72.722155 | O20: =N20/N19-1 -> 0.072628059

Sheet WACC
B2: Weighted Average Cost of Capital
B4: All figures are in INR unless stated otherwise
B6: Peer Companies
H8: Debt/ | I8: Debt/ | J8: Levered | K8: Unlevered
B9: Name of the Company | D9: Country | E9: Total Debt | F9: Total Equity | G9: Tax Rate 1 | H9: Equity | I9: Capital | J9: Beta 2 | K9: Beta 3
B10: Titan Company | D10: India | E10: 30621 | F10: 400897.6 | G10: 0.2517 | H10: =E10/F10 -> 0.076381101 | I10: =E10/(E10+F10) -> 0.07096102 | J10: ='Beta-Regression'!N8 -> 1.0389823 | K10: =J10/(1+(1-G10)*H10) -> 0.9828089
B11: Kalyan Jewellers | D11: India | E11: 6117.34 | F11: 54580.89 | G11: 0.2517 | H11: =E11/F11 -> 0.11207842 | I11: =E11/(E11+F11) -> 0.10078284 | J11: 1.87 | K11: =J11/(1+(1-G11)*H11) -> 1.7253019
B12: Lalithaa Jewel | D12: India | E12: 2045.4 | F12: 21708.34 | G12: 0.2517 | H12: =E12/F12 -> 0.094221852 | I12: =E12/(E12+F12) -> 0.086108545 | J12: 1.15 | K12: =J12/(1+(1-G12)*H12) -> 1.0742581
B13: Thangamayil Jew. | D13: India | E13: 913.21 | F13: 15108.97 | G13: 0.2517 | H13: =E13/F13 -> 0.060441579 | I13: =E13/(E13+F13) -> 0.056996613 | J13: 0.85 | K13: =J13/(1+(1-G13)*H13) -> 0.81321936
B14: PC Jeweller | D14: India | E14: 1166.56 | F14: 12573.54 | G14: 0.2517 | H14: =E14/F14 -> 0.092778963 | I14: =E14/(E14+F14) -> 0.084901857 | J14: 1.2 | K14: =J14/(1+(1-G14)*H14) -> 1.1220968
B15: Sky Gold & Diam. | D15: India | E15: 869.11 | F15: 12554.85 | G15: 0.2517 | H15: =E15/F15 -> 0.069225041 | I15: =E15/(E15+F15) -> 0.064743191 | J15: 1.2 | K15: =J15/(1+(1-G15)*H15) -> 1.1409001
B16: Bluestone Jewel | D16: India | E16: 1983.89 | F16: 12038.2 | G16: 0.2517 | H16: =E16/F16 -> 0.16479955 | I16: =E16/(E16+F16) -> 0.14148319 | J16: 1.28 | K16: =J16/(1+(1-G16)*H16) -> 1.1394799
F17: Average | G17: =AVERAGE(G11:G15) -> 0.2517 | H17: =AVERAGE(H11:H15) -> 0.085749171 | I17: =AVERAGE(I11:I15) -> 0.078706609 | J17: =AVERAGE(J11:J16) -> 1.2583333 | K17: =AVERAGE(K11:K16) -> 1.1692094
F18: Median | G18: =MEDIAN(G11:G15) -> 0.2517 | H18: =MEDIAN(H11:H15) -> 0.092778963 | I18: =MEDIAN(I11:I15) -> 0.084901857 | J18: =MEDIAN(J11:J15) -> 1.2 | K18: =MEDIAN(K11:K15) -> 1.1220968
B21: Cost of Debt | G21: Cost of Equity
B23: Pre-Tax cost of Debt | E23: =Historical_FS!L22/WACC!E10 -> 0.038535645 | G23: Risk Free Rate | K23: 0.072
B24: Tax Rate | E24: =G10 -> 0.2517 | G24: Equity Risk Premium | K24: =Rm!F7-WACC!K23 -> 0.092492308
B25: Post Tax Cost of Debt | E25: =E23*(1-E24) -> 0.028836224 | G25: Levered Beta 4 | K25: =K34 -> 1.2
G26: Cost of Equity | K26: =K23+(K24)*K25 -> 0.18299077
B29: Capital Structure | G29: Levered Beta
D31: Current | E31: Target | G31: Comps Median Unlevered Beta | K31: =K18 -> 1.1220968
B32: Total Debt | C32: =E10 -> 30621 | D32: =C32/$C$33 -> 0.076381101 | E32: =I18 -> 0.084901857 | G32: Target Debt/Equity | K32: =E36 -> 0.092778963
B33: Market Capitalization | C33: =F10 -> 400897.6 | D33: =D34-D32 -> 0.9236189 | E33: =E34-E32 -> 0.91509814 | G33: Tax Rate | K33: =G10 -> 0.2517
B34: Total Capital | C34: =SUM(C32:C33) -> 431518.6 | D34: 1 | E34: 1 | G34: Levered Data | K34: =K31*(1+(1-K33)*K32) -> 1.2
B36: Debt/Equity | D36: =D32/D33 -> 0.082697637 | E36: =E32/E33 -> 0.092778963 | G36: Weighted Average Cost of Capital
B38: Notes:- | G38: Cost of Equity | K38: =K26 -> 0.18299077
B39: 1. Tax Rate considered as Marginal Tax Rate for the country | G39: Equity Weight | K39: =E33 -> 0.91509814
B40: 2. Levered beta is based on 2 year weekly data
B41: 3. Unlevered Beta = levered Beta/ 1+(1- Tax Rate)* Debt/Equity) | G41: Cost of debt | K41: =E25 -> 0.028836224
B42: 4. Levered Beta= Unlevered Beta*(1+(1- Tax Rate)*Debt/Equity) | G42: Debt Weight | K42: =E32 -> 0.084901857
G43: WACC | K43: =(K38*K39)+(K41*K42) -> 0.16990276

Sheet Beta-Regression
B2: Regresion Beta
B4: Titan Company 2 years Weekly Return | F4: NSE Weekly 2 years Return | I4: Beta Drifting
B5: Date | C5: Price | D5: Return | F5: Price | G5: Return
B6: 46292 | C6: 4515.7 | D6: - | F6: 22421.95 | G6: - | I6: Levered Beta | K6: 1.04 | M6: Beta 1 | N6: =SLOPE(D7:D109,G7:G109) -> 1.0389823
B7: 46285 | C7: 4884 | D7: =(C7/C6)-1 -> 0.081559891 | F7: 23140.5 | G7: =(F7/F6)-1 -> 0.032046722 | I7: Raw Beta Weight | K7: 0.75 | M7: Beta 2 | N7: =_xlfn.COVARIANCE.S(D6:D109,G6:G109)/_xlfn.VAR.S(G6:G109) -> 1.0389823
B8: 46278 | C8: 4798.5 | D8: =(C8/C7)-1 -> -0.017506143 | F8: 23346.4 | G8: =(F8/F7)-1 -> 0.0088978198 | M8: Beta 3 | N8: =N31 -> 1.0389823
B9: 46271 | C9: 5009.5 | D9: =(C9/C8)-1 -> 0.043972075 | F9: 23398.1 | G9: =(F9/F8)-1 -> 0.0022144742 | I9: Market Beta | K9: 1
B10: 46264 | C10: 5020 | D10: =(C10/C9)-1 -> 0.0020960176 | F10: 23897.7 | G10: =(F10/F9)-1 -> 0.021352161 | I10: Market Beta Weight | K10: 0.25
B11: 46257 | C11: 5169.2 | D11: =(C11/C10)-1 -> 0.029721116 | F11: 24175.65 | G11: =(F11/F10)-1 -> 0.011630826
B12: 46250 | C12: 5086.1 | D12: =(C12/C11)-1 -> -0.016075989 | F12: 24252 | G12: =(F12/F11)-1 -> 0.0031581364 | I12: Adjusted Beta | K12: =(K6*K7)+(K9*K10) -> 1.03
B13: 46243 | C13: 5056.2 | D13: =(C13/C12)-1 -> -0.0058787676 | F13: 24366 | G13: =(F13/F12)-1 -> 0.0047006432
B14: 46236 | C14: 4941 | D14: =(C14/C13)-1 -> -0.022783909 | F14: 24570.65 | G14: =(F14/F13)-1 -> 0.0083989986 | M14: SUMMARY OUTPUT
B15: 46229 | C15: 4875.2 | D15: =(C15/C14)-1 -> -0.013317142 | F15: 24383.6 | G15: =(F15/F14)-1 -> -0.0076127412
B16: 46222 | C16: 4677 | D16: =(C16/C15)-1 -> -0.040654742 | F16: 23767.45 | G16: =(F16/F15)-1 -> -0.025269033 | M16: Regression Statistics
B17: 46215 | C17: 4638.1 | D17: =(C17/C16)-1 -> -0.0083172974 | F17: 24334.3 | G17: =(F17/F16)-1 -> 0.023849845 | M17: Multiple R | N17: 0.57722073
B18: 46208 | C18: 4584.4 | D18: =(C18/C17)-1 -> -0.011578017 | F18: 24206.9 | G18: =(F18/F17)-1 -> -0.0052354085 | M18: R Square | N18: 0.33318378
B19: 46201 | C19: 4461.1 | D19: =(C19/C18)-1 -> -0.026895559 | F19: 24270.85 | G19: =(F19/F18)-1 -> 0.0026418087 | M19: Adjusted R Square | N19: 0.32658164
B20: 46194 | C20: 4291.3 | D20: =(C20/C19)-1 -> -0.038062361 | F20: 24056 | G20: =(F20/F19)-1 -> -0.0088521828 | M20: Standard Error | N20: 0.026497713
B21: 46187 | C21: 4419.9 | D21: =(C21/C20)-1 -> 0.029967609 | F21: 24013.1 | G21: =(F21/F20)-1 -> -0.0017833389 | M21: Observations | N21: 103
B22: 46180 | C22: 4184 | D22: =(C22/C21)-1 -> -0.053372248 | F22: 23622.9 | G22: =(F22/F21)-1 -> -0.016249464
B23: 46173 | C23: 4260.2 | D23: =(C23/C22)-1 -> 0.018212237 | F23: 23366.7 | G23: =(F23/F22)-1 -> -0.010845408 | M23: ANOVA
B24: 46166 | C24: 4074.9 | D24: =(C24/C23)-1 -> -0.043495611 | F24: 23547.75 | G24: =(F24/F23)-1 -> 0.0077482058 | N24: df | O24: SS | P24: MS | Q24: F | R24: Significance F
B25: 46159 | C25: 4079.8 | D25: =(C25/C24)-1 -> 0.0012024835 | F25: 23719.3 | G25: =(F25/F24)-1 -> 0.0072851971 | M25: Regression | N25: 1 | O25: 0.035433647 | P25: 0.035433647 | Q25: 50.466021 | R25: 1.7442259e-10
B26: 46152 | C26: 4169.1 | D26: =(C26/C25)-1 -> 0.021888328 | F26: 23643.5 | G26: =(F26/F25)-1 -> -0.0031957098 | M26: Residual | N26: 101 | O26: 0.07091501 | P26: 0.00070212881
B27: 46145 | C27: 4509 | D27: =(C27/C26)-1 -> 0.081528387 | F27: 24176.15 | G27: =(F27/F26)-1 -> 0.02252839 | M27: Total | N27: 102 | O27: 0.10634866
B28: 46138 | C28: 4385.2 | D28: =(C28/C27)-1 -> -0.027456199 | F28: 23997.55 | G28: =(F28/F27)-1 -> -0.0073874459
B29: 46131 | C29: 4410 | D29: =(C29/C28)-1 -> 0.0056553863 | F29: 23897.95 | G29: =(F29/F28)-1 -> -0.0041504237 | N29: Coefficients | O29: Standard Error | P29: t Stat | Q29: P-value | R29: Lower 95% | S29: Upper 95% | T29: Lower 95.0% | U29: Upper 95.0%
B30: 46124 | C30: 4525.9 | D30: =(C30/C29)-1 -> 0.026281179 | F30: 24353.55 | G30: =(F30/F29)-1 -> 0.019064397 | M30: Intercept | N30: -0.0032777399 | O30: 0.0026168143 | P30: -1.2525688 | Q30: 0.21325516 | R30: -0.0084687955 | S30: 0.0019133157 | T30: -0.0084687955 | U30: 0.0019133157
B31: 46117 | C31: 4505 | D31: =(C31/C30)-1 -> -0.0046178661 | F31: 24050.6 | G31: =(F31/F30)-1 -> -0.012439665 | M31: X Variable 1 | N31: 1.0389823 | O31: 0.14625429 | P31: 7.103944 | Q31: 1.7442259e-10 | R31: 0.74885313 | S31: 1.3291115 | T31: 0.74885313 | U31: 1.3291115
B32: 46110 | C32: 4097.2 | D32: =(C32/C31)-1 -> -0.090521643 | F32: 22713.1 | G32: =(F32/F31)-1 -> -0.055611918
B33: 46103 | C33: 3981.5 | D33: =(C33/C32)-1 -> -0.028238797 | F33: 22819.6 | G33: =(F33/F32)-1 -> 0.004688924
B34: 46096 | C34: 4106.6 | D34: =(C34/C33)-1 -> 0.031420319 | F34: 23114.5 | G34: =(F34/F33)-1 -> 0.012923101
B35: 46089 | C35: 4073.2 | D35: =(C35/C34)-1 -> -0.0081332489 | F35: 23151.1 | G35: =(F35/F34)-1 -> 0.0015834217
B36: 46082 | C36: 4244.6 | D36: =(C36/C35)-1 -> 0.042079937 | F36: 24450.45 | G36: =(F36/F35)-1 -> 0.056124763
B37: 46075 | C37: 4327.5 | D37: =(C37/C36)-1 -> 0.019530698 | F37: 25178.65 | G37: =(F37/F36)-1 -> 0.029782683
B38: 46068 | C38: 4236.4 | D38: =(C38/C37)-1 -> -0.021051415 | F38: 25571.25 | G38: =(F38/F37)-1 -> 0.015592575
B39: 46061 | C39: 4179.2 | D39: =(C39/C38)-1 -> -0.01350203 | F39: 25471.1 | G39: =(F39/F38)-1 -> -0.0039165078
B40: 46054 | C40: 4141 | D40: =(C40/C39)-1 -> -0.0091405054 | F40: 25693.7 | G40: =(F40/F39)-1 -> 0.0087393163
B41: 46047 | C41: 3977.4 | D41: =(C41/C40)-1 -> -0.039507365 | F41: 25320.65 | G41: =(F41/F40)-1 -> -0.014519123
B42: 46040 | C42: 4021.8 | D42: =(C42/C41)-1 -> 0.011163071 | F42: 25048.65 | G42: =(F42/F41)-1 -> -0.01074222
B43: 46033 | C43: 4196.9 | D43: =(C43/C42)-1 -> 0.043537719 | F43: 25694.35 | G43: =(F43/F42)-1 -> 0.025777836
... B109: 45571 | C109: 3474.4 | D109: =(C109/C108)-1 -> 0.027488208 | F109: 24964.25 | G109: =(F109/F108)-1 -> 0.004433885

Sheet Rm
B2: Return of Market (NSE)
B4: Year | C4: Annual
B5: 2000 | C5: -0.1465 | E5: Average return | F5: =AVERAGE(C5:C30) -> 0.15149231
B6: 2001 | C6: -0.1618 | E6: Dividend Yield | F6: 0.013
B7: 2002 | C7: 0.0325 | E7: Total Market Return | F7: =SUM(F5:F6) -> 0.16449231
B8: 2003 | C8: 0.719
B9: 2004 | C9: 0.1068
B10: 2005 | C10: 0.3634
B11: 2006 | C11: 0.3983
B12: 2007 | C12: 0.5477
B13: 2008 | C13: -0.5179
B14: 2009 | C14: 0.7576
B15: 2010 | C15: 0.1795
B16: 2011 | C16: -0.2462
B17: 2012 | C17: 0.277
B18: 2013 | C18: 0.0676
B19: 2014 | C19: 0.3139
... B30: 2025 | C30: 0.1051

Sheet Intrinsic Growth
B3: Calculation of ROIC | F3: 44621 | G3: 44986 | H3: 45352 | I3: 45717 | J3: 46082
B5: Current Assets
B6: Inventories | F6: ='Raw Data'!J37 -> 13609 | G6: ='Raw Data'!K37 -> 16584 | H6: ='Raw Data'!L37 -> 19051 | I6: ='Raw Data'!M37 -> 28184 | J6: ='Raw Data'!N37 -> 42743
B7: Trade Receivables | F7: ='Raw Data'!J38 -> 565 | G7: ='Raw Data'!K38 -> 674 | H7: ='Raw Data'!L38 -> 1018 | I7: ='Raw Data'!M38 -> 1068 | J7: ='Raw Data'!N38 -> 916
B8: Loans n Advances | F8: ='Raw Data'!J40 -> 29 | G8: ='Raw Data'!K40 -> 167 | H8: ='Raw Data'!L40 -> 151 | I8: ='Raw Data'!M40 -> 324 | J8: ='Raw Data'!N40 -> 399
B9: Other assets items | F9: ='Raw Data'!J41 -> 2489 | G9: ='Raw Data'!K41 -> 2595 | H9: ='Raw Data'!L41 -> 3650 | I9: ='Raw Data'!M41 -> 3330 | J9: ='Raw Data'!N41 -> 4039
B10: Total Current Assets | F10: =SUM(F6:F9) -> 16692 | G10: =SUM(G6:G9) -> 20020 | H10: =SUM(H6:H9) -> 23870 | I10: =SUM(I6:I9) -> 32906 | J10: =SUM(J6:J9) -> 48097
B12: Current Liabilities
B13: Trade Payables | F13: ='Raw Data'!J14 -> 1294 | G13: ='Raw Data'!K14 -> 1214 | H13: ='Raw Data'!L14 -> 1410 | I13: ='Raw Data'!M14 -> 1963 | J13: ='Raw Data'!N14 -> 2864
B14: Advance from customers | F14: ='Raw Data'!J15 -> 532 | G14: ='Raw Data'!K15 -> 718 | H14: ='Raw Data'!L15 -> 1085 | I14: ='Raw Data'!M15 -> 2140 | J14: ='Raw Data'!N15 -> 4745
B15: Other Liability items | F15: ='Raw Data'!J16 -> 2754 | G15: ='Raw Data'!K16 -> 3817 | H15: ='Raw Data'!L16 -> 4131 | I15: ='Raw Data'!M16 -> 4141 | J15: ='Raw Data'!N16 -> 6628
B16: Total Current Liabilities | F16: =SUM(F13:F15) -> 4580 | G16: =SUM(G13:G15) -> 5749 | H16: =SUM(H13:H15) -> 6626 | I16: =SUM(I13:I15) -> 8244 | J16: =SUM(J13:J15) -> 14237
A18: # | B18: Net Working Capital | F18: =F10-F16 -> 12112 | G18: =G10-G16 -> 14271 | H18: =H10-H16 -> 17244 | I18: =I10-I16 -> 24662 | J18: =J10-J16 -> 33860
B20: Non Current Assets
B21: Land | F21: ='Raw Data'!J20 -> 136 | G21: ='Raw Data'!K20 -> 144 | H21: ='Raw Data'!L20 -> 163 | I21: ='Raw Data'!M20 -> 163 | J21: ='Raw Data'!N20 -> 440
B22: Building | F22: ='Raw Data'!J21 -> 1853 | G22: ='Raw Data'!K21 -> 2403 | H22: ='Raw Data'!L21 -> 3546 | I22: ='Raw Data'!M21 -> 4177 | J22: ='Raw Data'!N21 -> 5239
B23: Plant Machinery | F23: ='Raw Data'!J22 -> 768 | G23: ='Raw Data'!K22 -> 838 | H23: ='Raw Data'!L22 -> 899 | I23: ='Raw Data'!M22 -> 1012 | J23: ='Raw Data'!N22 -> 1197
B24: Equipments | F24: ='Raw Data'!J23 -> 96 | G24: ='Raw Data'!K23 -> 130 | H24: ='Raw Data'!L23 -> 110 | I24: ='Raw Data'!M23 -> 127 | J24: ='Raw Data'!N23 -> 176
B25: Computers | F25: ='Raw Data'!J24 -> 159 | G25: ='Raw Data'!K24 -> 204 | H25: ='Raw Data'!L24 -> 212 | I25: ='Raw Data'!M24 -> 228 | J25: ='Raw Data'!N24 -> 264
B26: Furniture n fittings | F26: ='Raw Data'!J25 -> 321 | G26: ='Raw Data'!K25 -> 376 | H26: ='Raw Data'!L25 -> 173 | I26: ='Raw Data'!M25 -> 193 | J26: ='Raw Data'!N25 -> 379
B27: Vehicles | F27: ='Raw Data'!J26 -> 38 | G27: ='Raw Data'!K26 -> 40 | H27: ='Raw Data'!L26 -> 50 | I27: ='Raw Data'!M26 -> 57 | J27: ='Raw Data'!N26 -> 68
B28: Intangible Assets | F28: ='Raw Data'!J27 -> 320 | G28: ='Raw Data'!K27 -> 320 | H28: ='Raw Data'!L27 -> 320 | I28: ='Raw Data'!M27 -> 320 | J28: ='Raw Data'!N27 -> 1782
B29: Other fixed assets | F29: ='Raw Data'!J28 -> 157 | G29: ='Raw Data'!K28 -> 205 | H29: ='Raw Data'!L28 -> 305 | I29: ='Raw Data'!M28 -> 369 | J29: ='Raw Data'!N28 -> 540
B30: Gross Block | F30: =SUM(F21:F29) -> 3848 | G30: =SUM(G21:G29) -> 4660 | H30: =SUM(H21:H29) -> 5778 | I30: =SUM(I21:I29) -> 6646 | J30: =SUM(J21:J29) -> 10085
B31: Accumulated Depreciation | F31: =-'Raw Data'!J30 -> -1304 | G31: =-'Raw Data'!K30 -> -1662 | H31: =-'Raw Data'!L30 -> -2069 | I31: =-'Raw Data'!M30 -> -2584 | J31: =-'Raw Data'!N30 -> -3207
A32: # | B32: Net Non Current Asset | F32: =SUM(F30:F31) -> 2544 | G32: =SUM(G30:G31) -> 2998 | H32: =SUM(H30:H31) -> 3709 | I32: =SUM(I30:I31) -> 4062 | J32: =SUM(J30:J31) -> 6878
A34: # | B34: Invested Capital | F34: =F32+F18 -> 14656 | G34: =G32+G18 -> 17269 | H34: =H32+H18 -> 20953 | I34: =I32+I18 -> 28724 | J34: =J32+J18 -> 40738
B35: Sales Growth | F35: =Historical_FS!H8 -> 0.3305766 | G35: =Historical_FS!I8 -> 0.40890309 | H35: =Historical_FS!J8 -> 0.25900185 | I35: =Historical_FS!K8 -> 0.18346253 | J35: =Historical_FS!L8 -> 0.44872304
B36: EBIT | F36: =Historical_FS!H28+Historical_FS!H22 -> 3122 | G36: =Historical_FS!I28+Historical_FS!I22 -> 4747 | H36: =Historical_FS!J28+Historical_FS!J22 -> 5242 | I36: =Historical_FS!K28+Historical_FS!K22 -> 5488 | J36: =Historical_FS!L28+Historical_FS!L22 -> 7981
B37: Marginal Tax Rate | F37: 0.25 | G37: 0.25 | H37: 0.25 | I37: 0.25 | J37: 0.25
B38: EBIT(1-T) | F38: =F36*(1-F37) -> 2341.5 | G38: =G36*(1-G37) -> 3560.25 | H38: =H36*(1-H37) -> 3931.5 | I38: =I36*(1-I37) -> 4116 | J38: =J36*(1-J37) -> 5985.75
A40: # | B40: ROIC | F40: =F38/F34 -> 0.15976392 | G40: =G38/G34 -> 0.20616422 | H40: =H38/H34 -> 0.18763423 | I40: =I38/I34 -> 0.14329481 | J40: =J38/J34 -> 0.14693284
B42: Calculation of Reinvestment Rate | F42: =F3 -> 44621 | G42: =G3 -> 44986 | H42: =H3 -> 45352 | I42: =I3 -> 45717 | J42: =J3 -> 46082
B44: Net Capex | F44: =-SUM('Cash Flow Data'!J16:J17) -> 216 | G44: =-SUM('Cash Flow Data'!K16:K17) -> 420 | H44: =-SUM('Cash Flow Data'!L16:L17) -> 671 | I44: =-SUM('Cash Flow Data'!M16:M17) -> 470 | J44: =-SUM('Cash Flow Data'!N16:N17) -> 877
B45: Change in Working Capital | F45: - | G45: =G18-F18 -> 2159 | H45: =H18-G18 -> 2973 | I45: =I18-H18 -> 7418 | J45: =J18-I18 -> 9198
B47: EBIT | F47: =F36 -> 3122 | G47: =G36 -> 4747 | H47: =H36 -> 5242 | I47: =I36 -> 5488 | J47: =J36 -> 7981
B48: Marginal Tax Rate | F48: 0.25 | G48: 0.25 | H48: 0.25 | I48: 0.25 | J48: 0.25
B49: EBIT(1-T) | F49: =F47*(1-F48) -> 2341.5 | G49: =G47*(1-G48) -> 3560.25 | H49: =H47*(1-H48) -> 3931.5 | I49: =I47*(1-I48) -> 4116 | J49: =J47*(1-J48) -> 5985.75
B50: Depreciation | F50: ='Data Sheet'!G26 -> 399 | G50: ='Data Sheet'!H26 -> 441 | H50: ='Data Sheet'!I26 -> 584 | I50: ='Data Sheet'!J26 -> 693 | J50: ='Data Sheet'!K26 -> 826
B51: Reinvestment | G51: =SUM(G44:G45) -> 2579 | H51: =SUM(H44:H45) -> 3644 | I51: =SUM(I44:I45) -> 7888 | J51: =SUM(J44:J45) -> 10075
B52: Reinvestment Rate | G52: =G51/G49 -> 0.72438733 | H52: =H51/H49 -> 0.92687269 | I52: =I51/I49 -> 1.9164237 | J52: =J51/J49 -> 1.6831642
H54: 4 year Average | J54: =AVERAGE(G52:J52) -> 1.312712
H55: 4 year Median | J55: =MEDIAN(G52:J52) -> 1.3050184
B57: Calculation of Growth Rate | F57: =F3 -> 44621 | G57: =G3 -> 44986 | H57: =H3 -> 45352 | I57: =I3 -> 45717 | J57: =J3 -> 46082
B59: Reinvestment Rate | G59: =G52 -> 0.72438733 | H59: =H52 -> 0.92687269 | I59: =I52 -> 1.9164237 | J59: =J52 -> 1.6831642
B60: ROIC | G60: =G40 -> 0.20616422 | H60: =H40 -> 0.18763423 | I60: =I40 -> 0.14329481 | J60: =J40 -> 0.14693284
B62: Intrinsic Growth Rate | G62: =G59*G60 -> 0.14934275 | H62: =H59*H60 -> 0.17391304 | I62: =I59*I60 -> 0.27461356 | J62: =J59*J60 -> 0.24731209
H64: 4 year Average | J64: =AVERAGE(G62:J62) -> 0.21129536
H65: 4 year Median | J65: =MEDIAN(G62:J62) -> 0.21061257

Sheet DCF
B2: Calculation of PV of FCFF | F2: ='Intrinsic Growth'!J3 -> 46082 | G2: =F2+365 -> 46447 | H2: =G2+366 -> 46813 | I2: =H2+365 -> 47178 | J2: =I2+365 -> 47543 | K2: =J2+365 -> 47908
B4: Sales | F4: {=TRANSPOSE(Forecasting!D15:D20)} -> 87584 | G4: 76085.763 | H4: 83367.664 | I4: 90649.564 | J4: 97931.464 | K4: 105213.36
B5: Sales Growth | F5: {=TRANSPOSE(Forecasting!E15:E20)} -> 0.44872304 | G5: -0.13128239 | H5: 0.095706475 | I5: 0.087346819 | J5: 0.080330229 | K5: 0.074357106
B6: EBIT | F6: =Historical_FS!L28+Historical_FS!L22 -> 7981 | G6: =F6*(1+$F$18) -> 9661.8989 | H6: =G6*(1+$F$18) -> 11696.816 | I6: =H6*(1+$F$18) -> 14160.313 | J6: =I6*(1+$F$18) -> 17142.653 | K6: =J6*(1+$F$18) -> 20753.111
B7: Depreciation | F7: =F4*(AVERAGE('Financials>'!H18:L18)) -> 999.32273 | G7: =G4*(AVERAGE('Financials>'!I18:M18)) -> 821.62621 | H7: =H4*(AVERAGE('Financials>'!J18:N18)) -> 914.72477 | I7: =I4*(AVERAGE('Financials>'!K18:O18)) -> 988.2392 | J7: =J4*(AVERAGE('Financials>'!L18:P18)) -> 1049.3073 | K7: =K4*(AVERAGE('Financials>'!M18:Q18)) -> 1194.8653
B8: Tax Rate | F8: =WACC!G10 -> 0.2517 | G8: =F8 -> 0.2517 | H8: =G8 -> 0.2517 | I8: =H8 -> 0.2517 | J8: =I8 -> 0.2517 | K8: =J8 -> 0.2517
B10: EBIT(1-Tax Rate)/ NOPAT | F10: =F6*(1-F8) -> 5972.1823 | G10: =G6*(1-G8) -> 7229.9989 | H10: =H6*(1-H8) -> 8752.7276 | I10: =I6*(1-I8) -> 10596.162 | J10: =J6*(1-J8) -> 12827.847 | K10: =K6*(1-K8) -> 15529.553
B11: Less: Reinvestment | F11: =-F10*(Assumptions!$C$16) -> -4479.1367 | G11: =-G10*(Assumptions!$C$16) -> -5422.4992 | H11: =-H10*(Assumptions!$C$16) -> -6564.5457 | I11: =-I10*(Assumptions!$C$16) -> -7947.1215 | J11: =-J10*(Assumptions!$C$16) -> -9620.8852 | K11: =-K10*(Assumptions!$C$16) -> -11647.165
B13: Free Cash Flow to Firm (FCFF) | F13: =SUM(F10:F11) -> 1493.0456 | G13: =SUM(G10:G11) -> 1807.4997 | H13: =SUM(H10:H11) -> 2188.1819 | I13: =SUM(I10:I11) -> 2649.0405 | J13: =SUM(J10:J11) -> 3206.9617 | K13: =SUM(K10:K11) -> 3882.3882
B14: Mid Year Convention | G14: 0.5 | H14: =G14+1 -> 1.5 | I14: =H14+1 -> 2.5 | J14: =I14+1 -> 3.5 | K14: =J14+1 -> 4.5
B15: Discounting Factor | G15: =1/(1+$F$20)^G14 -> 0.92453875 | H15: =1/(1+$F$20)^H14 -> 0.79026974 | I15: =1/(1+$F$20)^I14 -> 0.67550036 | J15: =1/(1+$F$20)^J14 -> 0.57739872 | K15: =1/(1+$F$20)^K14 -> 0.4935442
B16: PV of FCFF | G16: =G13*G15 -> 1671.1035 | H16: =H13*H15 -> 1729.2539 | I16: =I13*I15 -> 1789.4278 | J16: =J13*J15 -> 1851.6956 | K16: =K13*K15 -> 1916.1302
B18: Expected Growth | F18: ='Intrinsic Growth'!J65 -> 0.21061257
B19: Terminal growth | F19: 0.0575
B20: WACC | F20: =WACC!K43 -> 0.16990276
B22: Calculation of Terminal Value | H22: Senstivity Analysis
H23: =E40 -> 350.66693 | I23: 0.15 | J23: 0.16 | K23: =D25 -> 0.16990276 | L23: 0.17 | M23: 0.18
B24: FCFF(1+n) | D24: =K10*(1+F19)*(1-F19/F20) -> 10864.653 | H24: 0.03 | I24: 316.64718 | J24: 277.92954 | K24: 277.92954 | L24: 244.74298 | M24: 215.9813
B25: WACC | D25: =F20 -> 0.16990276 | H25: 0.04 | I25: 362.4044 | J25: 316.64718 | K25: 316.64718 | L25: 277.92954 | M25: 244.74298
B26: Terminal Growth Rate | D26: =F19 -> 0.0575 | H26: =D26 -> 0.0575 | I26: 362.4044 | J26: 316.64718 | K26: 316.64718 | L26: 277.92954 | M26: 244.74298
H27: 0.06 | I27: 484.42365 | J27: 417.31306 | K27: 417.31306 | L27: 362.4044 | M27: 316.64718
B28: Terminal Value | D28: =D24/(D25-D26) -> 96658.24 | H28: 0.07 | I28: 568.31188 | J28: 484.42365 | K28: 484.42365 | L28: 417.31306 | M28: 362.4044
B30: Calculation of Equity Value Per Share
B31: PV of FCFF | E31: =SUM(G16:K16) -> 8957.611
B32: PV of Terminal Value | E32: =D28*K15 -> 47705.114
B33: Value of Operating Asset | E33: =SUM(E31:E32) -> 56662.725
B35: Add: Cash | E35: ='Data Sheet'!K69 -> 1917
B36: Less: Debt | E36: =SUM('Raw Data'!N8:N9) -> 27448
B37: Value of Equity | E37: =E33+E35-E36 -> 31131.725
B38: No of shares | E38: ='Data Sheet'!B6 -> 88.778617
B40: Equity Value Per Share | E40: =E37/E38 -> 350.66693
B42: CMP | E42: ='Data Sheet'!B8 -> 4515.7
B43: Discount/ Premium | E43: =E42/E40-1 -> 11.877462

Sheet Relative_Valuation
B2: Figures in crores
B3: Comparable Company Valuation
C5: Market Value | I5: Financials | M5: Valuation
B6: Company | C6: Share Price | D6: Shares Outstanding | E6: Equity Value | F6: Net Debt | G6: Enterprise Value | I6: Revenue | J6: EBITDA | K6: Net Income | M6: EV/Revenue | N6: EV/EBITDA | O6: P/E
B9: =Data2!C5 -> Titan Company | C9: =Data2!D5 -> 4420.55 | D9: =Data2!E5 -> 88.78 | E9: =C9*D9 -> 392456.43 | F9: =Data2!I5 -> 28704 | G9: =Data2!J5 -> 421160.43 | I9: =Data2!K5 -> 92417 | J9: =Data2!L5 -> 10012 | K9: =Data2!M5 -> 5760 | M9: =G9/I9 -> 4.5571749 | N9: =G9/J9 -> 42.065564 | O9: =E9/K9 -> 68.134797
B10: =Data2!C6 -> Kalyan Jewellers | C10: =Data2!D6 -> 553.6 | D10: =Data2!E6 -> 103.28 | E10: =C10*D10 -> 57175.808 | F10: =Data2!I6 -> 5256.43 | G10: =Data2!J6 -> 62432.238 | I10: =Data2!K6 -> 39063.32 | J10: =Data2!L6 -> 2833.19 | K10: =Data2!M6 -> 1434.98 | M10: =G10/I10 -> 1.5982317 | N10: =G10/J10 -> 22.036022 | O10: =E10/K10 -> 39.844324
B11: =Data2!C7 -> Lalithaa Jewel | C11: =Data2!D7 -> 381.9 | D11: =Data2!E7 -> 55.97 | E11: =C11*D11 -> 21374.943 | F11: =Data2!I7 -> 2007.34 | G11: =Data2!J7 -> 23382.283 | I11: =Data2!K7 -> 25039.04 | J11: =Data2!L7 -> 1734.55 | K11: =Data2!M7 -> 1008.79 | M11: =G11/I11 -> 0.93383305 | N11: =G11/J11 -> 13.480317 | O11: =E11/K11 -> 21.188694
B12: =Data2!C8 -> Thangamayil Jew. | C12: =Data2!D8 -> 4905.2 | D12: =Data2!E8 -> 3.11 | E12: =C12*D12 -> 15255.172 | F12: =Data2!I8 -> 531.98 | G12: =Data2!J8 -> 15787.152 | I12: =Data2!K8 -> 9622.28 | J12: =Data2!L8 -> 636.82 | K12: =Data2!M8 -> 391.04 | M12: =G12/I12 -> 1.6406872 | N12: =G12/J12 -> 24.790603 | O12: =E12/K12 -> 39.011794
B13: =Data2!C9 -> PC Jeweller | C13: =Data2!D9 -> 14.95 | D13: =Data2!E9 -> 980.78 | E13: =C13*D13 -> 14662.661 | F13: =Data2!I9 -> 1030.39 | G13: =Data2!J9 -> 15693.051 | I13: =Data2!K9 -> 3505.01 | J13: =Data2!L9 -> 901.35 | K13: =Data2!M9 -> 774.41 | M13: =G13/I13 -> 4.4773199 | N13: =G13/J13 -> 17.410607 | O13: =E13/K13 -> 18.933977
B14: =Data2!C10 -> Sky Gold & Diam. | C14: =Data2!D10 -> 923.6 | D14: =Data2!E10 -> 15.49 | E14: =C14*D14 -> 14306.564 | F14: =Data2!I10 -> 633.66 | G14: =Data2!J10 -> 14940.224 | I14: =Data2!K10 -> 7176.44 | J14: =Data2!L10 -> 559.72 | K14: =Data2!M10 -> 343.15 | M14: =G14/I14 -> 2.0818434 | N14: =G14/J14 -> 26.692318 | O14: =E14/K14 -> 41.691867
B15: =Data2!C11 -> Bluestone Jewel | C15: =Data2!D11 -> 822 | D15: =Data2!E11 -> 15.28 | E15: =C15*D15 -> 12560.16 | F15: =Data2!I11 -> 1472.22 | G15: =Data2!J11 -> 14032.38 | I15: =Data2!K11 -> 2680.6 | J15: =Data2!L11 -> 488.49 | K15: =Data2!M11 -> 53.89 | M15: =G15/I15 -> 5.2347907 | N15: =G15/J15 -> 28.726033 | O15: =E15/K15 -> 233.07033
B16: =Data2!C12 -> P N Gadgil Jewe. | C16: =Data2!D12 -> 599.95 | D16: =Data2!E12 -> 14.72 | E16: =C16*D16 -> 8831.264 | F16: =Data2!I12 -> 1232.64 | G16: =Data2!J12 -> 10063.904 | I16: =Data2!K12 -> 11437.52 | J16: =Data2!L12 -> 773.39 | K16: =Data2!M12 -> 445.82 | M16: =G16/I16 -> 0.87990264 | N16: =G16/J16 -> 13.012715 | O16: =E16/K16 -> 19.809035
B17: =Data2!C13 -> Timex Group | C17: =Data2!D13 -> 728.05 | D17: =Data2!E13 -> 10.1 | E17: =C17*D17 -> 7353.305 | F17: =Data2!I13 -> 37.44 | G17: =Data2!J13 -> 7390.745 | I17: =Data2!K13 -> 848.55 | J17: =Data2!L13 -> 129.97 | K17: =Data2!M13 -> 85.79 | M17: =G17/I17 -> 8.7098521 | N17: =G17/J17 -> 56.865007 | O17: =E17/K17 -> 85.712845
B18: =Data2!C14 -> Ethos | C18: =Data2!D14 -> 2575.05 | D18: =Data2!E14 -> 2.68 | E18: =C18*D18 -> 6901.134 | F18: =Data2!I14 -> -339.33 | G18: =Data2!J14 -> 6561.804 | I18: =Data2!K14 -> 1727.63 | J18: =Data2!L14 -> 271.77 | K18: =Data2!M14 -> 105.78 | M18: =G18/I18 -> 3.7981535 | N18: =G18/J18 -> 24.144696 | O18: =E18/K18 -> 65.240442
B20: High | M20: =MAX(M9:M18) -> 8.7098521 | N20: =MAX(N9:N18) -> 56.865007 | O20: =MAX(O9:O18) -> 233.07033
B21: 75th Percentile | M21: =_xlfn.QUARTILE.INC(M9:M18,3) -> 4.5372111 | N21: =_xlfn.QUARTILE.INC(N9:N18,3) -> 28.217604 | O21: =_xlfn.QUARTILE.INC(O9:O18,3) -> 67.411208
B22: Average | M22: =AVERAGE(M10:M18) -> 3.2616238 | N22: =AVERAGE(N10:N18) -> 25.239813 | O22: =AVERAGE(O10:O18) -> 62.72259
B23: Median | M23: =MEDIAN(M9:M18) -> 2.9399985 | N23: =MEDIAN(N9:N18) -> 24.46765 | O23: =MEDIAN(O9:O18) -> 40.768095
B24: 25th Percentile | M24: =_xlfn.QUARTILE.INC(M9:M18,1) -> 1.6088456 | N24: =_xlfn.QUARTILE.INC(N9:N18,1) -> 18.566961 | O24: =_xlfn.QUARTILE.INC(O9:O18,1) -> 25.644469
B25: Low | M25: =MIN(M9:M18) -> 0.87990264 | N25: =MIN(N9:N18) -> 13.012715 | O25: =MIN(O9:O18) -> 18.933977
B27: Titan Comparable Valuation | M27: EV/Revenue | N27: EV/EBITDA | O27: P/E
B29: Implied Enterprise Value | M29: =M23*I9 -> 271705.84 | N29: =N23*J9 -> 244970.11 | O29: =O31+O30 -> 263528.23
B30: Net Debt | M30: =F9 -> 28704 | N30: =M30 -> 28704 | O30: =N30 -> 28704
B31: Implied Market Value | M31: =M29-M30 -> 243001.84 | N31: =N29-N30 -> 216266.11 | O31: =O23*K9 -> 234824.23
B32: Shares Outstanding | M32: =D9 -> 88.78 | N32: =M32 -> 88.78 | O32: =M32 -> 88.78
B34: Implied Value Per Share | M34: =M31/M32 -> 2737.1236 | N34: =N31/N32 -> 2435.9778 | O34: =O31/O32 -> 2645.0127
B35: Source: screener.in
M36: =IF(M34>$C$9,"Undervalued","Overvalued") -> Overvalued | N36: =IF(N34>$C$9,"Undervalued","Overvalued") -> Overvalued | O36: =IF(O34>$C$9,"Undervalued","Overvalued") -> Overvalued
B37: Author_ Farheen Ahmed Only for educational purpose

Sheet Football Field Analysis
K3: Football Field Analysis- Data
M4: Open/Low | N4: Low | O4: Open/High | P4: High
K5: Comps | M5: =Relative_Valuation!N34 -> 2435.9778 | N5: =M5 -> 2435.9778 | O5: =Relative_Valuation!M34 -> 2737.1236 | P5: =O5 -> 2737.1236
K6: DCF Bear | M6: =DCF!M24 -> 215.9813 | N6: =M6 -> 215.9813 | O6: =DCF!M28 -> 362.4044 | P6: =O6 -> 362.4044
K7: DCF Base | M7: =DCF!K24 -> 277.92954 | N7: =M7 -> 277.92954 | O7: =DCF!K28 -> 484.42365 | P7: =O7 -> 484.42365
K8: DCF bull | M8: =DCF!I24 -> 316.64718 | N8: =M8 -> 316.64718 | O8: =DCF!I28 -> 568.31188 | P8: =O8 -> 568.31188
K9: 52W H/L | M9: 3500 | N9: =M9 -> 3500 | O9: =P9 -> 5187 | P9: 5187

Sheet VaR
B3: Date | C3: Price | D3: Sorted Return | F3: Calculation of VaR for Titan Company Ltd (Historical Data)
B4: 46304 | C4: 4406.4 | D4: 0.010758114
B5: 46303 | C5: 4359.5 | D5: -0.0039981723 | F5: Mean | J5: =AVERAGE(D4:D685) -> 0.00036504918
B6: 46302 | C6: 4377 | D6: -0.038021978 | F6: Standard Deviation | J6: =_xlfn.STDEV.S(D4:D685) -> 0.014594659
B7: 46301 | C7: 4550 | D7: -0.0065502183 | F7: Min | J7: =MIN(D4:D685) -> -0.071804522
B8: 46300 | C8: 4580 | D8: 0.01423921 | F8: Max | J8: =MAX(D4:D685) -> 0.065264484
B9: 46296 | C9: 4515.7 | D9: -0.015543928 | F9: CMP | J9: 4406.4
B10: 46295 | C10: 4587 | D10: -0.018823529
B11: 46294 | C11: 4675 | D11: -0.029982363 | F11: Percentile | G11: Confidence | H11: Var % | I11: Stock Price | J11: VaR
B12: 46293 | C12: 4819.5 | D12: -0.013206388 | F12: 0.05 | G12: =100%-F12 -> 0.95 | H12: =_xlfn.PERCENTILE.INC(D4:D685,F12) -> -0.020871637 | I12: =$J$9*(1-H12) -> 4498.3688 | J12: =$J$9-I12 -> -91.968781
B13: 46290 | C13: 4884 | D13: 0.01065701 | F13: 0.01 | G13: =100%-F13 -> 0.99 | H13: =_xlfn.PERCENTILE.INC(D5:D686,F13) -> -0.035378318 | I13: =$J$9*(1-H13) -> 4562.291 | J13: =$J$9-I13 -> -155.89102
B14: 46289 | C14: 4832.5 | D14: -0.0097336066 | F14: 0.005 | G14: =100%-F14 -> 0.995 | H14: =_xlfn.PERCENTILE.INC(D6:D687,F14) -> -0.054972062 | I14: =$J$9*(1-H14) -> 4648.6289 | J14: =$J$9-I14 -> -242.2289
B15: 46288 | C15: 4880 | D15: -0.0098407223
B16: 46287 | C16: 4928.5 | D16: 0.010974359
B17: 46286 | C17: 4875 | D17: 0.015942482
B18: 46283 | C18: 4798.5 | D18: -0.0087791779
B19: 46282 | C19: 4841 | D19: -0.013751655
B20: 46281 | C20: 4908.5 | D20: 0.010811367
B21: 46280 | C21: 4856 | D21: -0.030641781
B22: 46276 | C22: 5009.5 | D22: -0.0022903804
B23: 46275 | C23: 5021 | D23: 0.0031968032
B24: 46274 | C24: 5005 | D24: 0.0036093844
B25: 46273 | C25: 4987 | D25: -0.0016016016
B26: 46272 | C26: 4995 | D26: -0.0049800797
... B685: 45301 | C685: 3714.45 | D685: 0.0055360043

Sheet Mont_Carlo
B3: Date | C3: Price | D3: Sorted Return | E3: Replication | F3: Stimulated Returns | I3: Calculation of VaR for Titan Company Ltd (Historical Data)
B4: 46304 | C4: 4406.4 | D4: 0.010758114 | E4: 1 | F4: =_xlfn.NORM.INV(RAND(),M$6,M$7) -> 0.0261848
B5: 46303 | C5: 4359.5 | D5: -0.0039981723 | E5: 2 | F5: =_xlfn.NORM.INV(RAND(),M$6,M$7) -> -0.0040216227 | I5: Historical Approach
B6: 46302 | C6: 4377 | D6: -0.038021978 | E6: 3 | F6: =_xlfn.NORM.INV(RAND(),M$6,M$7) -> 0.0022439877 | I6: Mean | M6: =AVERAGE(D4:D685) -> 0.00036504918
B7: 46301 | C7: 4550 | D7: -0.0065502183 | E7: 4 | F7: =_xlfn.NORM.INV(RAND(),M$6,M$7) -> 0.0043693395 | I7: Standard Deviation | M7: =_xlfn.STDEV.S(D4:D685) -> 0.014594659
B8: 46300 | C8: 4580 | D8: 0.01423921 | E8: 5 | F8: =_xlfn.NORM.INV(RAND(),M$6,M$7) -> 0.02026712 | I8: Min | M8: =MIN(D4:D685) -> -0.071804522
B9: 46296 | C9: 4515.7 | D9: -0.015543928 | E9: 6 | F9: =_xlfn.NORM.INV(RAND(),M$6,M$7) -> 0.028082701 | I9: Max | M9: =MAX(D4:D685) -> 0.065264484
B10: 46295 | C10: 4587 | D10: -0.018823529 | E10: 7 | F10: =_xlfn.NORM.INV(RAND(),M$6,M$7) -> 0.020801258 | I10: CMP | M10: 4406.4
B11: 46294 | C11: 4675 | D11: -0.029982363 | E11: 8 | F11: =_xlfn.NORM.INV(RAND(),M$6,M$7) -> 0.0013626679
B12: 46293 | C12: 4819.5 | D12: -0.013206388 | E12: 9 | F12: =_xlfn.NORM.INV(RAND(),M$6,M$7) -> 0.013900175 | I12: Monte-Carlo Stimulations
B13: 46290 | C13: 4884 | D13: 0.01065701 | E13: 10 | F13: =_xlfn.NORM.INV(RAND(),M$6,M$7) -> 0.0045375982 | I13: Mean | M13: =AVERAGE(F4:F10003) -> 0.00033169485
B14: 46289 | C14: 4832.5 | D14: -0.0097336066 | E14: 11 | F14: =_xlfn.NORM.INV(RAND(),M$6,M$7) -> 0.02222102 | I14: Standard Deviation | M14: =_xlfn.STDEV.S(F4:F10003) -> 0.014844599
B15: 46288 | C15: 4880 | D15: -0.0098407223 | E15: 12 | F15: =_xlfn.NORM.INV(RAND(),M$6,M$7) -> 0.0012581089 | I15: Min | M15: =MIN(F4:F10003) -> -0.055316208
B16: 46287 | C16: 4928.5 | D16: 0.010974359 | E16: 13 | F16: =_xlfn.NORM.INV(RAND(),M$6,M$7) -> -0.0015188642 | I16: Max | M16: =MAX(F4:F10003) -> 0.05417848
B17: 46286 | C17: 4875 | D17: 0.015942482 | E17: 14 | F17: =_xlfn.NORM.INV(RAND(),M$6,M$7) -> 0.025483478 | I17: CMP | M17: 4406.4
B18: 46283 | C18: 4798.5 | D18: -0.0087791779 | E18: 15 | F18: =_xlfn.NORM.INV(RAND(),M$6,M$7) -> -0.028722817
B19: 46282 | C19: 4841 | D19: -0.013751655 | E19: 16 | F19: =_xlfn.NORM.INV(RAND(),M$6,M$7) -> 0.0045159287 | I19: Percentile | J19: Confidence | K19: Var % | L19: Stock Price | M19: VaR
B20: 46281 | C20: 4908.5 | D20: 0.010811367 | E20: 17 | F20: =_xlfn.NORM.INV(RAND(),M$6,M$7) -> 0.007986665 | I20: 0.05 | J20: =100%-I20 -> 0.95 | K20: =_xlfn.PERCENTILE.INC(F4:F10003,I20) -> -0.023983072 | L20: =$M$10*(1-K20) -> 4512.079 | M20: =$M$10-L20 -> -105.67901
B21: 46280 | C21: 4856 | D21: -0.030641781 | E21: 18 | F21: =_xlfn.NORM.INV(RAND(),M$6,M$7) -> -0.01144854 | I21: 0.01 | J21: =100%-I21 -> 0.99 | K21: =_xlfn.PERCENTILE.INC(F4:F10003,I21) -> -0.034278997 | L21: =$M$10*(1-K21) -> 4557.447 | M21: =$M$10-L21 -> -151.04697
B22: 46276 | C22: 5009.5 | D22: -0.0022903804 | E22: 19 | F22: =_xlfn.NORM.INV(RAND(),M$6,M$7) -> 0.018468508 | I22: 0.005 | J22: =100%-I22 -> 0.995 | K22: =_xlfn.PERCENTILE.INC(F4:F10003,I22) -> -0.037856549 | L22: =$M$10*(1-K22) -> 4573.2111 | M22: =$M$10-L22 -> -166.8111
B23: 46275 | C23: 5021 | D23: 0.0031968032 | E23: 20 | F23: =_xlfn.NORM.INV(RAND(),M$6,M$7) -> -0.0099481102
B24: 46274 | C24: 5005 | D24: 0.0036093844 | E24: 21 | F24: =_xlfn.NORM.INV(RAND(),M$6,M$7) -> 0.031900869
B25: 46273 | C25: 4987 | D25: -0.0016016016 | E25: 22 | F25: =_xlfn.NORM.INV(RAND(),M$6,M$7) -> 0.010970693
B26: 46272 | C26: 4995 | D26: -0.0049800797 | E26: 23 | F26: =_xlfn.NORM.INV(RAND(),M$6,M$7) -> 0.012303247
B27: 46269 | C27: 5020 | D27: -0.0013924806 | E27: 24 | F27: =_xlfn.NORM.INV(RAND(),M$6,M$7) -> 0.017379366
B28: 46268 | C28: 5027 | D28: -0.0092629089 | E28: 25 | F28: =_xlfn.NORM.INV(RAND(),M$6,M$7) -> -0.027490253
B29: 46267 | C29: 5074 | D29: 0.0047524752 | E29: 26 | F29: =_xlfn.NORM.INV(RAND(),M$6,M$7) -> -0.012712666
B30: 46266 | C30: 5050 | D30: -0.010269677 | E30: 27 | F30: =_xlfn.NORM.INV(RAND(),M$6,M$7) -> -0.010350947
B31: 46265 | C31: 5102.4 | D31: -0.012922696 | E31: 28 | F31: =_xlfn.NORM.INV(RAND(),M$6,M$7) -> -0.038967627
B32: 46262 | C32: 5169.2 | D32: 0.0058179129 | E32: 29 | F32: =_xlfn.NORM.INV(RAND(),M$6,M$7) -> -0.0057862652
B33: 46261 | C33: 5139.3 | D33: 0.0077058824 | E33: 30 | F33: =_xlfn.NORM.INV(RAND(),M$6,M$7) -> 0.010388335
B34: 46260 | C34: 5100 | D34: -0.0048392132 | E34: 31 | F34: =_xlfn.NORM.INV(RAND(),M$6,M$7) -> 0.013888667
... B685: 45301 | C685: 3714.45 | D685: 0.0055360043 | E685: 682 | F685: =_xlfn.NORM.INV(RAND(),M$6,M$7) -> -0.01386274
E686: 683 | F686: =_xlfn.NORM.INV(RAND(),M$6,M$7) -> -0.002582973
E687: 684 | F687: =_xlfn.NORM.INV(RAND(),M$6,M$7) -> -0.013219807
E688: 685 | F688: =_xlfn.NORM.INV(RAND(),M$6,M$7) -> -0.011113164
E689: 686 | F689: =_xlfn.NORM.INV(RAND(),M$6,M$7) -> -0.014990285
E690: 687 | F690: =_xlfn.NORM.INV(RAND(),M$6,M$7) -> -0.0034223295
E691: 688 | F691: =_xlfn.NORM.INV(RAND(),M$6,M$7) -> -0.012027281
E692: 689 | F692: =_xlfn.NORM.INV(RAND(),M$6,M$7) -> 0.016992198
E693: 690 | F693: =_xlfn.NORM.INV(RAND(),M$6,M$7) -> 0.027868693
E694: 691 | F694: =_xlfn.NORM.INV(RAND(),M$6,M$7) -> 0.014087058
E695: 692 | F695: =_xlfn.NORM.INV(RAND(),M$6,M$7) -> -0.026002971
E696: 693 | F696: =_xlfn.NORM.INV(RAND(),M$6,M$7) -> 0.017989351
E697: 694 | F697: =_xlfn.NORM.INV(RAND(),M$6,M$7) -> 0.024162428
... E10003: 10000 | F10003: =_xlfn.NORM.INV(RAND(),M$6,M$7) -> 0.00068628826

Sheet Data2
B2: Relative Valuation
B4: S.No. | C4: Company | D4: CMP | E4: No. Eq. Shares | F4: Market Cap | G4: Debt | H4: Cash End | I4: Net Debt | J4: EV | K4: Sales | L4: EBITDA | M4: Netprofit
B5: 1 | C5: Titan Company | D5: 4420.55 | E5: 88.78 | F5: =D5*E5 -> 392456.43 | G5: 30621 | H5: 1917 | I5: =G5-H5 -> 28704 | J5: =F5+G5-H5 -> 421160.43 | K5: 92417 | L5: 10012 | M5: 5760
B6: 2 | C6: Kalyan Jewellers | D6: 553.6 | E6: 103.28 | F6: =D6*E6 -> 57175.808 | G6: 6117.34 | H6: 860.91 | I6: =G6-H6 -> 5256.43 | J6: =F6+G6-H6 -> 62432.238 | K6: 39063.32 | L6: 2833.19 | M6: 1434.98
B7: 3 | C7: Lalithaa Jewel | D7: 381.9 | E7: 55.97 | F7: =D7*E7 -> 21374.943 | G7: 2045.4 | H7: 38.06 | I7: =G7-H7 -> 2007.34 | J7: =F7+G7-H7 -> 23382.283 | K7: 25039.04 | L7: 1734.55 | M7: 1008.79
B8: 4 | C8: Thangamayil Jew. | D8: 4905.2 | E8: 3.11 | F8: =D8*E8 -> 15255.172 | G8: 913.21 | H8: 381.23 | I8: =G8-H8 -> 531.98 | J8: =F8+G8-H8 -> 15787.152 | K8: 9622.28 | L8: 636.82 | M8: 391.04
B9: 5 | C9: PC Jeweller | D9: 14.95 | E9: 980.78 | F9: =D9*E9 -> 14662.661 | G9: 1166.56 | H9: 136.17 | I9: =G9-H9 -> 1030.39 | J9: =F9+G9-H9 -> 15693.051 | K9: 3505.01 | L9: 901.35 | M9: 774.41
B10: 6 | C10: Sky Gold & Diam. | D10: 923.6 | E10: 15.49 | F10: =D10*E10 -> 14306.564 | G10: 869.1 | H10: 235.44 | I10: =G10-H10 -> 633.66 | J10: =F10+G10-H10 -> 14940.224 | K10: 7176.44 | L10: 559.72 | M10: 343.15
B11: 7 | C11: Bluestone Jewel | D11: 822 | E11: 15.28 | F11: =D11*E11 -> 12560.16 | G11: 1983.89 | H11: 511.67 | I11: =G11-H11 -> 1472.22 | J11: =F11+G11-H11 -> 14032.38 | K11: 2680.6 | L11: 488.49 | M11: 53.89
B12: 8 | C12: P N Gadgil Jewe. | D12: 599.95 | E12: 14.72 | F12: =D12*E12 -> 8831.264 | G12: 1737.09 | H12: 504.45 | I12: =G12-H12 -> 1232.64 | J12: =F12+G12-H12 -> 10063.904 | K12: 11437.52 | L12: 773.39 | M12: 445.82
B13: 9 | C13: Timex Group | D13: 728.05 | E13: 10.1 | F13: =D13*E13 -> 7353.305 | G13: 71.41 | H13: 33.97 | I13: =G13-H13 -> 37.44 | J13: =F13+G13-H13 -> 7390.745 | K13: 848.55 | L13: 129.97 | M13: 85.79
B14: 10 | C14: Ethos | D14: 2575.05 | E14: 2.68 | F14: =D14*E14 -> 6901.134 | G14: 322.32 | H14: 661.65 | I14: =G14-H14 -> -339.33 | J14: =F14+G14-H14 -> 6561.804 | K14: 1727.63 | L14: 271.77 | M14: 105.78
B25: 11 | C25: Senco Gold | D25: 335.9 | E25: 16.39 | F25: =D25*E25 -> 5505.401 | G25: 2699.11 | H25: 516.64 | J25: =F25+G25-H25 -> 7687.871 | K25: 9659.79 | L25: 1075.07 | M25: 570.8
B26: 12 | C26: D.P. Abhushan | D26: 2339.3 | E26: 2.28 | F26: =D26*E26 -> 5333.604 | G26: 303.83 | H26: 25.75 | J26: =F26+G26-H26 -> 5611.684 | K26: 4377.16 | L26: 348.43 | M26: 239.86
B27: 13 | C27: KDDL Ltd | D27: 3773.4 | E27: 1.23 | F27: =D27*E27 -> 4641.282 | G27: 511.83 | H27: 735.04 | J27: =F27+G27-H27 -> 4418.072 | K27: 2322.23 | L27: 305.45 | M27: 150.24
B28: 14 | C28: Goldiam Intl. | D28: 308.1 | E28: 15.06 | F28: =D28*E28 -> 4639.986 | G28: 77.01 | H28: 306.02 | J28: =F28+G28-H28 -> 4410.976 | K28: 1073.15 | L28: 391.04 | M28: 210.96
B29: 15 | C29: T B Z | D29: 596.15 | E29: 6.67 | F29: =D29*E29 -> 3976.3205 | G29: 886.21 | H29: 101.83 | J29: =F29+G29-H29 -> 4760.7005 | K29: 3419.92 | L29: 387.28 | M29: 213.72
B30: 16 | C30: Vaibhav Global | D30: 201.8 | E30: 16.78 | F30: =D30*E30 -> 3386.204 | G30: 415.84 | H30: 371.39 | J30: =F30+G30-H30 -> 3430.654 | K30: 3795.13 | L30: 426.92 | M30: 284.87
B31: 17 | C31: Shanti Gold | D31: 387.5 | E31: 7.67 | F31: =D31*E31 -> 2972.125 | G31: 216.24 | H31: 49.18 | J31: =F31+G31-H31 -> 3139.185 | K31: 2442.32 | L31: 269.55 | M31: 186.36
B32: 18 | C32: Deepa Jewellers | D32: 246 | E32: 9.61 | F32: =D32*E32 -> 2364.06 | G32: 116.78 | H32: 0.1 | J32: =F32+G32-H32 -> 2480.74 | K32: 1926.68 | L32: 147.38 | M32: 104.79
B33: 19 | C33: PNGS Reva Diamo. | D33: 688.35 | E33: 3.17 | F33: =D33*E33 -> 2182.0695 | G33: 169.71 | H33: 324.23 | J33: =F33+G33-H33 -> 2027.5495 | K33: 503.25 | L33: 124.64 | M33: 84.41
B34: 20 | C34: Shringar House | D34: 221.3 | E34: 9.64 | F34: =D34*E34 -> 2133.332 | G34: 189.09 | H34: 127.24 | J34: =F34+G34-H34 -> 2195.182 | K34: 2461.71 | L34: 172.36 | M34: 120.99
B35: 21 | C35: Motisons Jewel | D35: 17.89 | E35: 113.75 | F35: =D35*E35 -> 2034.9875 | G35: 38.91 | H35: 15.73 | J35: =F35+G35-H35 -> 2058.1675 | K35: 509.83 | L35: 96.87 | M35: 66.72
B36: 22 | C36: Utssav CZ Gold | D36: 837.3 | E36: 2.41 | F36: =D36*E36 -> 2017.893 | G36: 186.22 | H36: 51.57 | J36: =F36+G36-H36 -> 2152.543 | K36: 1154.9 | L36: 93.7 | M36: 59.06
... B39: 25 | C39: Renaiss. Global | D39: 160.7 | E39: 10.74 | F39: =D39*E39 -> 1725.918 | G39: 641.37 | H39: 107.48 | J39: =F39+G39-H39 -> 2259.808 | K39: 3063.16 | L39: 398.69 | M39: 109.3

Sheet Raw Data
B3: Particulars | C3: 42064 | D3: 42430 | E3: 42795 | F3: 43160 | G3: 43525 | H3: 43891 | I3: 44256 | J3: 44621 | K3: 44986 | L3: 45352 | M3: 45717 | N3: 46082
B5: Equity Capital | C5: 89 | D5: 89 | E5: 89 | F5: 89 | G5: 89 | H5: 89 | I5: 89 | J5: 89 | K5: 89 | L5: 89 | M5: 89 | N5: 89
B6: Reserves | C6: 2995 | D6: 3418 | E6: 4144 | F6: 5001 | G6: 5981 | H6: 6580 | I6: 7408 | J6: 9214 | K6: 11762 | L6: 9304 | M6: 11535 | N6: 15614
B7: Borrowings -
B8: Long term Borrowings | C8: 0 | D8: 0 | E8: 0 | F8: 0 | G8: 32 | H8: 17 | I8: 9 | J8: 2 | K8: 0 | L8: 3302 | M8: 595 | N8: 93
B9: Short term Borrowings | C9: 100 | D9: 113 | E9: 1882 | F9: 1691 | G9: 2353 | H9: 2291 | I9: 4367 | J9: 5914 | K9: 7494 | L9: 9877 | M9: 17501 | N9: 27355
B10: Lease Liabilities | C10: 0 | D10: 0 | E10: 0 | F10: 0 | G10: 0 | H10: 1243 | I10: 1256 | J10: 1359 | K10: 1873 | L10: 2349 | M10: 2681 | N10: 3173
B11: Other Borrowings | C11: 0 | D11: 0 | E11: 0 | F11: 0 | G11: 8 | H11: 11 | I11: 6 | J11: 0 | K11: 0 | L11: 0 | M11: 0 | N11: 0
B12: Other Liabilities -
B13: Non controlling int | C13: 0 | D13: 0 | E13: 26 | F13: -2 | G13: 14 | H13: 4 | I13: 5 | J13: 30 | K13: 53 | L13: 0 | M13: 0 | N13: 0
B14: Trade Payables | C14: 1940 | D14: 1655 | E14: 783 | F14: 878 | G14: 906 | H14: 596 | I14: 789 | J14: 1294 | K14: 1214 | L14: 1410 | M14: 1963 | N14: 2864
B15: Advance from Customers | C15: 160 | D15: 710 | E15: 943 | F15: 233 | G15: 290 | H15: 386 | I15: 479 | J15: 532 | K15: 718 | L15: 1085 | M15: 2140 | N15: 4745
B16: Other liability items | C16: 585 | D16: 358 | E16: 541 | F16: 1631 | G16: 2037 | H16: 2327 | I16: 2036 | J16: 2754 | K16: 3817 | L16: 4131 | M16: 4141 | N16: 6628
B17: Total Liabilities | C17: 5868 | D17: 6342 | E17: 8408 | F17: 9521 | G17: 11710 | H17: 13544 | I17: 16444 | J17: 21188 | K17: 27020 | L17: 31547 | M17: 40645 | N17: 60561
B19: Fixed Assets -
B20: Land | C20: 104 | D20: 85 | E20: 85 | F20: 85 | G20: 85 | H20: 108 | I20: 108 | J20: 136 | K20: 144 | L20: 163 | M20: 163 | N20: 440
B21: Building | C21: 156 | D21: 137 | E21: 198 | F21: 341 | G21: 386 | H21: 1473 | I21: 1617 | J21: 1853 | K21: 2403 | L21: 3546 | M21: 4177 | N21: 5239
B22: Plant Machinery | C22: 719 | D22: 445 | E22: 473 | F22: 563 | G22: 630 | H22: 724 | I22: 739 | J22: 768 | K22: 838 | L22: 899 | M22: 1012 | N22: 1197
B23: Equipments | C23: 24 | D23: 18 | E23: 24 | F23: 34 | G23: 50 | H23: 70 | I23: 76 | J23: 96 | K23: 130 | L23: 110 | M23: 127 | N23: 176
B24: Computers | C24: 0 | D24: 0 | E24: 46 | F24: 72 | G24: 92 | H24: 119 | I24: 142 | J24: 159 | K24: 204 | L24: 212 | M24: 228 | N24: 264
B25: Furniture n fittings | C25: 189 | D25: 107 | E25: 138 | F25: 203 | G25: 251 | H25: 313 | I25: 309 | J25: 321 | K25: 376 | L25: 173 | M25: 193 | N25: 379
B26: Vehicles | C26: 17 | D26: 11 | E26: 10 | F26: 16 | G26: 22 | H26: 28 | I26: 30 | J26: 38 | K26: 40 | L26: 50 | M26: 57 | N26: 68
B27: Intangible Assets | C27: 0 | D27: 13 | E27: 318 | F27: 319 | G27: 319 | H27: 333 | I27: 320 | J27: 320 | K27: 320 | L27: 320 | M27: 320 | N27: 1782
B28: Other fixed assets | C28: 73 | D28: 20 | E28: 26 | F28: 69 | G28: 96 | H28: 135 | I28: 158 | J28: 157 | K28: 205 | L28: 305 | M28: 369 | N28: 540
B29: Gross Block | C29: 1282 | D29: 836 | E29: 1318 | F29: 1704 | G29: 1931 | H29: 3303 | I29: 3499 | J29: 3848 | K29: 4660 | L29: 5778 | M29: 6646 | N29: 10085
B30: Accumulated Depreciation | C30: 583 | D30: 66 | E30: 130 | F30: 230 | G30: 365 | H30: 670 | I30: 976 | J30: 1304 | K30: 1662 | L30: 2069 | M30: 2584 | N30: 3207
B31: Net Block | C31: =SUM(C29:C30) -> 1865 | D31: =SUM(D29:D30) -> 902 | E31: =SUM(E29:E30) -> 1448 | F31: =SUM(F29:F30) -> 1934 | G31: =SUM(G29:G30) -> 2296 | H31: =SUM(H29:H30) -> 3973 | I31: =SUM(I29:I30) -> 4475 | J31: =SUM(J29:J30) -> 5152 | ... N31: =SUM(N29:N30) -> 13292
B33: CWIP | C33: 55 | D33: 107 | E33: 152 | F33: 43 | G33: 32 | H33: 18 | I33: 32 | J33: 85 | K33: 144 | L33: 97 | M33: 105 | N33: 163
B34: Investments | C34: 3 | D34: 30 | E34: 431 | F34: 36 | G34: 108 | H34: 158 | I34: 2824 | J34: 294 | K34: 2515 | L34: 2345 | M34: 1988 | N34: 3506
B36: Other Assets -
B37: Inventories | C37: 4049 | D37: 4447 | E37: 4926 | F37: 5925 | G37: 7039 | H37: 8103 | I37: 8408 | J37: 13609 | K37: 16584 | L37: 19051 | M37: 28184 | N37: 42743
B38: Trade receivables | C38: 190 | D38: 192 | E38: 208 | F38: 296 | G38: 420 | H38: 312 | I38: 366 | J38: 565 | K38: 674 | L38: 1018 | M38: 1068 | N38: 916
B39: Cash Equivalents | C39: 214 | D39: 116 | E39: 779 | F39: 618 | G39: 1066 | H39: 381 | I39: 560 | J39: 1573 | K39: 1343 | L39: 1526 | M39: 1584 | N39: 1917
B40: Loans n Advances | C40: 47 | D40: 87 | E40: 122 | F40: 141 | G40: 25 | H40: 142 | I40: 109 | J40: 29 | K40: 167 | L40: 151 | M40: 324 | N40: 399
B41: Other asset items | C41: 611 | D41: 591 | E41: 602 | F41: 988 | G41: 1452 | H41: 1797 | I41: 1622 | J41: 2489 | K41: 2595 | L41: 3650 | M41: 3330 | N41: 4039
B42: Total Assets | C42: 5868 | D42: 6342 | E42: 8408 | F42: 9521 | G42: 11710 | H42: 13544 | I42: 16444 | J42: 21188 | K42: 27020 | L42: 31547 | M42: 40645 | N42: 60561

Sheet Cash Flow Data
B1: ="Financial Model:" & 'Data Sheet'!B1 -> Financial Model:TITAN COMPANY LTD
B2: Cash Flow Data
B3: Particulars | C3: 42078 | D3: 42445 | E3: 42795 | F3: 43160 | G3: 43525 | H3: 43891 | I3: 44256 | J3: 44621 | K3: 44986 | L3: 45352 | M3: 45717 | N3: 46082
B5: Cash from Operating Activity - | E5: 1712 | F5: -51 | G5: 1243 | H5: -348 | I5: 4139 | J5: -724 | K5: 1370 | L5: 1695 | M5: -541 | N5: 5590
B6: Profit from operations | E6: 1073 | F6: 1642 | G6: 2183 | H6: 2481 | I6: 1789 | J6: 3298 | K6: 4937 | L6: 5404 | M6: 5774 | N6: 8447
B7: Receivables | E7: -12 | F7: -90 | G7: -139 | H7: 109 | I7: -59 | J7: -207 | K7: -112 | L7: -348 | M7: -95 | N7: 210
B8: Inventory | E8: -448 | F8: -996 | G8: -1120 | H8: -1057 | I8: -316 | J8: -5199 | K8: -2977 | L8: -2462 | M8: -9072 | N8: -11592
B9: Payables | E9: 238 | F9: 95 | G9: 32 | H9: -310 | I9: 195 | J9: 504 | K9: -89 | L9: 196 | M9: 564 | N9: 472
B10: Loans Advances | E10: 0 | F10: 3 | G10: -24 | H10: -20 | I10: -8 | J10: -3 | K10: -18 | L10: -21 | M10: 4 | N10: -8
B11: Operating borrowings | E11: 763 | F11: -270 | G11: 741 | H11: -768 | I11: 2625 | J11: 1188 | K11: -99 | L11: 42 | M11: 2468 | N11: 7304
B12: Other WC items | E12: 375 | F12: 22 | G12: 206 | H12: -226 | I12: 184 | J12: 497 | K12: 882 | L12: 57 | M12: 905 | N12: 2494
B13: Working capital changes | E13: 916 | F13: -1237 | G13: -304 | H13: -2272 | I13: 2621 | J13: -3220 | K13: -2413 | L13: -2536 | M13: -5226 | N13: -1120
B14: Direct taxes | E14: -277 | F14: -456 | G14: -636 | H14: -557 | I14: -271 | J14: -802 | K14: -1154 | L14: -1173 | M14: -1089 | N14: -1737
B15: Cash from Investing Activity - | E15: -953 | F15: 98 | G15: -797 | H15: 235 | I15: -2799 | J15: 1165 | K15: -1814 | L15: -189 | M15: 546 | N15: -2965
B16: Fixed assets purchased | E16: -256 | F16: -305 | G16: -265 | H16: -355 | I16: -146 | J16: -224 | K16: -432 | L16: -691 | M16: -494 | N16: -902
... B35: CFO/OP | E35: 1.71 | F35: 0.25 | G35: 0.94 | H35: 0.08 | I35: 2.56 | J35: 0.02 | K35: 0.52 | L35: 0.54 | M35: 0.1 | N35: 0.88
